[
  {
    "n": "1.40",
    "tagname": "pb",
    "char_offset": 0,
    "token_offset": null,
    "urn": null
  },
  {
    "n": 1,
    "tagname": "lb",
    "char_offset": 26,
    "page": "1.40",
    "token_offset": "DOCTRINA[1]",
    "urn": "urn:cts:greekLit:tlg0057.tlg002.verbatim-lat1:1"
  },
  {
    "tagname": "head",
    "char_offset": 0,
    "line": 1,
    "page": "1.40",
    "token_offset": null,
    "urn": "urn:cts:greekLit:tlg0057.tlg002.verbatim-lat1:1",
    "end_char_offset": 26,
    "end_token_offset": "DOCTRINA[1]"
  },
  {
    "n": 2,
    "tagname": "lb",
    "char_offset": 33,
    "page": "1.40",
    "token_offset": "LIBER.[1]",
    "urn": "urn:cts:greekLit:tlg0057.tlg002.verbatim-lat1:1"
  },
  {
    "rend": "indent",
    "tagname": "p",
    "char_offset": 33,
    "line": 2,
    "page": "1.40",
    "token_offset": "LIBER.[1]",
    "urn": "urn:cts:greekLit:tlg0057.tlg002.verbatim-lat1:1",
    "end_char_offset": 33,
    "end_token_offset": "LIBER.[1]"
  },
  {
    "value": "1",
    "tagname": "num",
    "char_offset": 33,
    "line": 3,
    "page": "1.40",
    "token_offset": "LIBER.[1]",
    "urn": "urn:cts:greekLit:tlg0057.tlg002.verbatim-lat1:1",
    "end_char_offset": 41,
    "end_token_offset": "I.[1]"
  },
  {
    "type": "head",
    "tagname": "label",
    "char_offset": 33,
    "line": 3,
    "page": "1.40",
    "token_offset": "LIBER.[1]",
    "urn": "urn:cts:greekLit:tlg0057.tlg002.verbatim-lat1:1",
    "end_char_offset": 41,
    "end_token_offset": "I.[1]"
  },
  {
    "n": 3,
    "tagname": "lb",
    "char_offset": 76,
    "page": "1.40",
    "token_offset": "partem[1]",
    "urn": "urn:cts:greekLit:tlg0057.tlg002.verbatim-lat1:1"
  },
  {
    "n": 4,
    "tagname": "lb",
    "char_offset": 127,
    "page": "1.40",
    "token_offset": "autem[1]",
    "urn": "urn:cts:greekLit:tlg0057.tlg002.verbatim-lat1:1"
  },
  {
    "n": 5,
    "tagname": "lb",
    "char_offset": 175,
    "page": "1.40",
    "token_offset": "oppositum[1]",
    "urn": "urn:cts:greekLit:tlg0057.tlg002.verbatim-lat1:1"
  },
  {
    "n": 6,
    "tagname": "lb",
    "char_offset": 230,
    "page": "1.40",
    "token_offset": "terminari[1]",
    "urn": "urn:cts:greekLit:tlg0057.tlg002.verbatim-lat1:1"
  },
  {
    "n": 7,
    "tagname": "lb",
    "char_offset": 293,
    "page": "1.40",
    "token_offset": "indefinitionem,[1]",
    "urn": "urn:cts:greekLit:tlg0057.tlg002.verbatim-lat1:1"
  },
  {
    "rend": "italic",
    "tagname": "hi",
    "char_offset": 293,
    "line": 8,
    "page": "1.40",
    "token_offset": "indefinitionem,[1]",
    "urn": "urn:cts:greekLit:tlg0057.tlg002.verbatim-lat1:1",
    "end_char_offset": 312,
    "end_token_offset": "judicium[1]"
  },
  {
    "n": 8,
    "tagname": "lb",
    "char_offset": 335,
    "page": "1.40",
    "token_offset": "re[1]",
    "urn": "urn:cts:greekLit:tlg0057.tlg002.verbatim-lat1:1"
  },
  {
    "n": 9,
    "tagname": "lb",
    "char_offset": 387,
    "page": "1.40",
    "token_offset": "autem[2]",
    "urn": "urn:cts:greekLit:tlg0057.tlg002.verbatim-lat1:1"
  },
  {
    "n": 10,
    "tagname": "lb",
    "char_offset": 437,
    "page": "1.40",
    "token_offset": "promovent[1]",
    "urn": "urn:cts:greekLit:tlg0057.tlg002.verbatim-lat1:1"
  },
  {
    "n": 11,
    "tagname": "lb",
    "char_offset": 498,
    "page": "1.40",
    "token_offset": "comprehensibilem:[1]",
    "urn": "urn:cts:greekLit:tlg0057.tlg002.verbatim-lat1:1"
  },
  {
    "n": "1.41",
    "tagname": "pb",
    "char_offset": 546,
    "token_offset": "promovent,[1]",
    "urn": "urn:cts:greekLit:tlg0057.tlg002.verbatim-lat1:1"
  },
  {
    "n": 1,
    "tagname": "lb",
    "char_offset": 546,
    "page": "1.41",
    "token_offset": "promovent,[1]",
    "urn": "urn:cts:greekLit:tlg0057.tlg002.verbatim-lat1:1"
  },
  {
    "n": 2,
    "tagname": "lb",
    "char_offset": 596,
    "page": "1.41",
    "token_offset": "edoctis[1]",
    "urn": "urn:cts:greekLit:tlg0057.tlg002.verbatim-lat1:1"
  },
  {
    "n": 3,
    "tagname": "lb",
    "char_offset": 654,
    "page": "1.41",
    "token_offset": "est,[1]",
    "urn": "urn:cts:greekLit:tlg0057.tlg002.verbatim-lat1:1"
  },
  {
    "n": 4,
    "tagname": "lb",
    "char_offset": 712,
    "page": "1.41",
    "token_offset": "Academica,[1]",
    "urn": "urn:cts:greekLit:tlg0057.tlg002.verbatim-lat1:1"
  },
  {
    "n": 5,
    "tagname": "lb",
    "char_offset": 769,
    "page": "1.41",
    "token_offset": "ad[1]",
    "urn": "urn:cts:greekLit:tlg0057.tlg002.verbatim-lat1:1"
  },
  {
    "n": 6,
    "tagname": "lb",
    "char_offset": 828,
    "page": "1.41",
    "token_offset": "servus,[1]",
    "urn": "urn:cts:greekLit:tlg0057.tlg002.verbatim-lat1:1"
  },
  {
    "n": 7,
    "tagname": "lb",
    "char_offset": 886,
    "page": "1.41",
    "token_offset": "postea[1]",
    "urn": "urn:cts:greekLit:tlg0057.tlg002.verbatim-lat1:1"
  },
  {
    "n": 8,
    "tagname": "lb",
    "char_offset": 950,
    "page": "1.41",
    "token_offset": "disputantes[1]",
    "urn": "urn:cts:greekLit:tlg0057.tlg002.verbatim-lat1:1"
  },
  {
    "n": 9,
    "tagname": "lb",
    "char_offset": 1002,
    "page": "1.41",
    "token_offset": "permittentes[1]",
    "urn": "urn:cts:greekLit:tlg0057.tlg002.verbatim-lat1:1"
  },
  {
    "n": 10,
    "tagname": "lb",
    "char_offset": 1062,
    "page": "1.41",
    "token_offset": "quidem[3]",
    "urn": "urn:cts:greekLit:tlg0057.tlg002.verbatim-lat1:1"
  },
  {
    "n": 11,
    "tagname": "lb",
    "char_offset": 1125,
    "page": "1.41",
    "token_offset": "comprehensibile;[1]",
    "urn": "urn:cts:greekLit:tlg0057.tlg002.verbatim-lat1:1"
  },
  {
    "n": 12,
    "tagname": "lb",
    "char_offset": 1176,
    "page": "1.41",
    "token_offset": "certo[2]",
    "urn": "urn:cts:greekLit:tlg0057.tlg002.verbatim-lat1:1"
  },
  {
    "n": 13,
    "tagname": "lb",
    "char_offset": 1237,
    "page": "1.41",
    "token_offset": "comprehensibile,[1]",
    "urn": "urn:cts:greekLit:tlg0057.tlg002.verbatim-lat1:1"
  },
  {
    "n": 14,
    "tagname": "lb",
    "char_offset": 1294,
    "page": "1.41",
    "token_offset": "mirabar,[1]",
    "urn": "urn:cts:greekLit:tlg0057.tlg002.verbatim-lat1:1"
  },
  {
    "n": 15,
    "tagname": "lb",
    "char_offset": 1346,
    "page": "1.41",
    "token_offset": "singula[1]",
    "urn": "urn:cts:greekLit:tlg0057.tlg002.verbatim-lat1:1"
  },
  {
    "n": 16,
    "tagname": "lb",
    "char_offset": 1406,
    "page": "1.41",
    "token_offset": "comprehensibile,[2]",
    "urn": "urn:cts:greekLit:tlg0057.tlg002.verbatim-lat1:1"
  },
  {
    "n": 17,
    "tagname": "lb",
    "char_offset": 1465,
    "page": "1.41",
    "token_offset": "imaginationem;[1]",
    "urn": "urn:cts:greekLit:tlg0057.tlg002.verbatim-lat1:1"
  },
  {
    "n": "1.42",
    "tagname": "pb",
    "char_offset": 1513,
    "token_offset": "dicuntur,[1]",
    "urn": "urn:cts:greekLit:tlg0057.tlg002.verbatim-lat1:1"
  },
  {
    "n": 1,
    "tagname": "lb",
    "char_offset": 1513,
    "page": "1.42",
    "token_offset": "dicuntur,[1]",
    "urn": "urn:cts:greekLit:tlg0057.tlg002.verbatim-lat1:1"
  },
  {
    "n": 2,
    "tagname": "lb",
    "char_offset": 1576,
    "page": "1.42",
    "token_offset": "incomprehensionem.[1]",
    "urn": "urn:cts:greekLit:tlg0057.tlg002.verbatim-lat1:1"
  },
  {
    "n": 3,
    "tagname": "lb",
    "char_offset": 1615,
    "page": "1.42",
    "token_offset": "ad[2]",
    "urn": "urn:cts:greekLit:tlg0057.tlg002.verbatim-lat1:1"
  },
  {
    "n": 4,
    "tagname": "lb",
    "char_offset": 1674,
    "page": "1.42",
    "token_offset": "Aristarchum;[1]",
    "urn": "urn:cts:greekLit:tlg0057.tlg002.verbatim-lat1:1"
  },
  {
    "n": 5,
    "tagname": "lb",
    "char_offset": 1726,
    "page": "1.42",
    "token_offset": "comprehensiva,[1]",
    "urn": "urn:cts:greekLit:tlg0057.tlg002.verbatim-lat1:1"
  },
  {
    "n": 6,
    "tagname": "lb",
    "char_offset": 1776,
    "page": "1.42",
    "token_offset": "conatus[1]",
    "urn": "urn:cts:greekLit:tlg0057.tlg002.verbatim-lat1:1"
  },
  {
    "type": "textpart",
    "subtype": "chapter",
    "n": "1",
    "content": "GALENI DE OPTIMA DOCTRINA LIBER. Cap. I. Argumentationem in utramque partem optimam esse doctrinam censet Favorinus. Sic autem nominant Academici eam, secundum quam oppositum enunciant. Antiquiores igitur eam in epochen terminari autumant, epochen vocantes, ac si quis dixerit indefinitionem, ancepsque judicium , quod est nulla de re determinare, nec certo enunciare. Recentiores autem (non enim solus Favorinus) aliquando eo promovent epochen, ut ne solem quidem fateantur esse comprehensibilem: aliquando vero in tantum cognitionem promovent, ut discipulis eam permittant nondum prius edoctis de scientifico judicandi instrumento. Nec enim aliud est, quod Favorinus dixit in libro de constitutione Academica, qui Plutarchus inscribitur. Idem autem dicit in libro ad Epictetum, in quo scilicet est Onesimus, Plutarchi servus, cum Epicteto disputans; ac certe eo in libro, quem postea scripsit, Alcibiadem et caeteros Academicos laudat, disputantes quidem inter se contrariis rationibus, permittentes autem discipulis ex his eligere veriores; sed in hoc quidem ipso dixit, probabile sibi videri, nihil esse comprehensibile; in Plutarcho vero concedere videtur, aliquid certo posse cognosci; praestat enim sic appellare comprehensibile, abstinentes a Stoico nomine. Atque ego per Deos mirabar, quomodo Favorinus assuetus Atticae dictioni singula nomina commutare non desinat, dicens neque comprehensibile, neque comprehensionem, neque comprehensivam imaginationem; neque his opposita, ut quae privative dicuntur, incomprehensibilem imaginationem, vel ipsam incomprehensionem. Ut autem tres libros scripsit, unum ad Adrianum, secundum ad Drusonem, et tertium ad Aristarchum; hos omnes inscripsit de imaginatione comprehensiva, et per omnes hos libros strenue disputat, conatus demonstrare, non dari comprehensivam imaginationem.",
    "line": 7,
    "page": "1.42",
    "tokens": [
      "GALENI",
      "DE",
      "OPTIMA",
      "DOCTRINA",
      "LIBER.",
      "Cap.",
      "I.",
      "Argumentationem",
      "in",
      "utramque",
      "partem",
      "optimam",
      "esse",
      "doctrinam",
      "censet",
      "Favorinus.",
      "Sic",
      "autem",
      "nominant",
      "Academici",
      "eam,",
      "secundum",
      "quam",
      "oppositum",
      "enunciant.",
      "Antiquiores",
      "igitur",
      "eam",
      "in",
      "epochen",
      "terminari",
      "autumant,",
      "epochen",
      "vocantes,",
      "ac",
      "si",
      "quis",
      "dixerit",
      "indefinitionem,",
      "ancepsque",
      "judicium",
      ",",
      "quod",
      "est",
      "nulla",
      "de",
      "re",
      "determinare,",
      "nec",
      "certo",
      "enunciare.",
      "Recentiores",
      "autem",
      "(non",
      "enim",
      "solus",
      "Favorinus)",
      "aliquando",
      "eo",
      "promovent",
      "epochen,",
      "ut",
      "ne",
      "solem",
      "quidem",
      "fateantur",
      "esse",
      "comprehensibilem:",
      "aliquando",
      "vero",
      "in",
      "tantum",
      "cognitionem",
      "promovent,",
      "ut",
      "discipulis",
      "eam",
      "permittant",
      "nondum",
      "prius",
      "edoctis",
      "de",
      "scientifico",
      "judicandi",
      "instrumento.",
      "Nec",
      "enim",
      "aliud",
      "est,",
      "quod",
      "Favorinus",
      "dixit",
      "in",
      "libro",
      "de",
      "constitutione",
      "Academica,",
      "qui",
      "Plutarchus",
      "inscribitur.",
      "Idem",
      "autem",
      "dicit",
      "in",
      "libro",
      "ad",
      "Epictetum,",
      "in",
      "quo",
      "scilicet",
      "est",
      "Onesimus,",
      "Plutarchi",
      "servus,",
      "cum",
      "Epicteto",
      "disputans;",
      "ac",
      "certe",
      "eo",
      "in",
      "libro,",
      "quem",
      "postea",
      "scripsit,",
      "Alcibiadem",
      "et",
      "caeteros",
      "Academicos",
      "laudat,",
      "disputantes",
      "quidem",
      "inter",
      "se",
      "contrariis",
      "rationibus,",
      "permittentes",
      "autem",
      "discipulis",
      "ex",
      "his",
      "eligere",
      "veriores;",
      "sed",
      "in",
      "hoc",
      "quidem",
      "ipso",
      "dixit,",
      "probabile",
      "sibi",
      "videri,",
      "nihil",
      "esse",
      "comprehensibile;",
      "in",
      "Plutarcho",
      "vero",
      "concedere",
      "videtur,",
      "aliquid",
      "certo",
      "posse",
      "cognosci;",
      "praestat",
      "enim",
      "sic",
      "appellare",
      "comprehensibile,",
      "abstinentes",
      "a",
      "Stoico",
      "nomine.",
      "Atque",
      "ego",
      "per",
      "Deos",
      "mirabar,",
      "quomodo",
      "Favorinus",
      "assuetus",
      "Atticae",
      "dictioni",
      "singula",
      "nomina",
      "commutare",
      "non",
      "desinat,",
      "dicens",
      "neque",
      "comprehensibile,",
      "neque",
      "comprehensionem,",
      "neque",
      "comprehensivam",
      "imaginationem;",
      "neque",
      "his",
      "opposita,",
      "ut",
      "quae",
      "privative",
      "dicuntur,",
      "incomprehensibilem",
      "imaginationem,",
      "vel",
      "ipsam",
      "incomprehensionem.",
      "Ut",
      "autem",
      "tres",
      "libros",
      "scripsit,",
      "unum",
      "ad",
      "Adrianum,",
      "secundum",
      "ad",
      "Drusonem,",
      "et",
      "tertium",
      "ad",
      "Aristarchum;",
      "hos",
      "omnes",
      "inscripsit",
      "de",
      "imaginatione",
      "comprehensiva,",
      "et",
      "per",
      "omnes",
      "hos",
      "libros",
      "strenue",
      "disputat,",
      "conatus",
      "demonstrare,",
      "non",
      "dari",
      "comprehensivam",
      "imaginationem."
    ],
    "urn": "urn:cts:greekLit:tlg0057.tlg002.verbatim-lat1:1"
  },
  {
    "n": 7,
    "tagname": "lb",
    "char_offset": 0,
    "page": "1.42",
    "token_offset": null,
    "urn": "urn:cts:greekLit:tlg0057.tlg002.verbatim-lat1:2"
  },
  {
    "rend": "indent",
    "tagname": "p",
    "char_offset": 0,
    "line": 7,
    "page": "1.42",
    "token_offset": null,
    "urn": "urn:cts:greekLit:tlg0057.tlg002.verbatim-lat1:2",
    "end_char_offset": 0,
    "end_token_offset": null
  },
  {
    "value": "2",
    "tagname": "num",
    "char_offset": 0,
    "line": 8,
    "page": "1.42",
    "token_offset": null,
    "urn": "urn:cts:greekLit:tlg0057.tlg002.verbatim-lat1:2",
    "end_char_offset": 9,
    "end_token_offset": "II.[1]"
  },
  {
    "type": "head",
    "tagname": "label",
    "char_offset": 0,
    "line": 8,
    "page": "1.42",
    "token_offset": null,
    "urn": "urn:cts:greekLit:tlg0057.tlg002.verbatim-lat1:2",
    "end_char_offset": 9,
    "end_token_offset": "II.[1]"
  },
  {
    "n": 8,
    "tagname": "lb",
    "char_offset": 51,
    "page": "1.42",
    "token_offset": "puto[1]",
    "urn": "urn:cts:greekLit:tlg0057.tlg002.verbatim-lat1:2"
  },
  {
    "n": 9,
    "tagname": "lb",
    "char_offset": 110,
    "page": "1.42",
    "token_offset": "comprehendere,[1]",
    "urn": "urn:cts:greekLit:tlg0057.tlg002.verbatim-lat1:2"
  },
  {
    "n": 10,
    "tagname": "lb",
    "char_offset": 155,
    "page": "1.42",
    "token_offset": "dici[1]",
    "urn": "urn:cts:greekLit:tlg0057.tlg002.verbatim-lat1:2"
  },
  {
    "n": 11,
    "tagname": "lb",
    "char_offset": 204,
    "page": "1.42",
    "token_offset": "imaginationem.[1]",
    "urn": "urn:cts:greekLit:tlg0057.tlg002.verbatim-lat1:2"
  },
  {
    "n": 12,
    "tagname": "lb",
    "char_offset": 257,
    "page": "1.42",
    "token_offset": "vel[3]",
    "urn": "urn:cts:greekLit:tlg0057.tlg002.verbatim-lat1:2"
  },
  {
    "n": 13,
    "tagname": "lb",
    "char_offset": 309,
    "page": "1.42",
    "token_offset": "deliriis;[1]",
    "urn": "urn:cts:greekLit:tlg0057.tlg002.verbatim-lat1:2"
  },
  {
    "n": 14,
    "tagname": "lb",
    "char_offset": 364,
    "page": "1.42",
    "token_offset": "videmus,[1]",
    "urn": "urn:cts:greekLit:tlg0057.tlg002.verbatim-lat1:2"
  },
  {
    "n": 15,
    "tagname": "lb",
    "char_offset": 416,
    "page": "1.42",
    "token_offset": "posteriora[1]",
    "urn": "urn:cts:greekLit:tlg0057.tlg002.verbatim-lat1:2"
  },
  {
    "n": 16,
    "tagname": "lb",
    "char_offset": 465,
    "page": "1.42",
    "token_offset": "Pyrrhonios,[1]",
    "urn": "urn:cts:greekLit:tlg0057.tlg002.verbatim-lat1:2"
  },
  {
    "n": 17,
    "tagname": "lb",
    "char_offset": 517,
    "page": "1.42",
    "token_offset": "per[1]",
    "urn": "urn:cts:greekLit:tlg0057.tlg002.verbatim-lat1:2"
  },
  {
    "n": 18,
    "tagname": "lb",
    "char_offset": 572,
    "page": "1.42",
    "token_offset": "esse[1]",
    "urn": "urn:cts:greekLit:tlg0057.tlg002.verbatim-lat1:2"
  },
  {
    "n": "1.43",
    "tagname": "pb",
    "char_offset": 622,
    "token_offset": "concedant,[1]",
    "urn": "urn:cts:greekLit:tlg0057.tlg002.verbatim-lat1:2"
  },
  {
    "n": 1,
    "tagname": "lb",
    "char_offset": 622,
    "page": "1.43",
    "token_offset": "concedant,[1]",
    "urn": "urn:cts:greekLit:tlg0057.tlg002.verbatim-lat1:2"
  },
  {
    "n": 2,
    "tagname": "lb",
    "char_offset": 681,
    "page": "1.43",
    "token_offset": "neque[2]",
    "urn": "urn:cts:greekLit:tlg0057.tlg002.verbatim-lat1:2"
  },
  {
    "n": 3,
    "tagname": "lb",
    "char_offset": 735,
    "page": "1.43",
    "token_offset": "vigilantem[1]",
    "urn": "urn:cts:greekLit:tlg0057.tlg002.verbatim-lat1:2"
  },
  {
    "n": 4,
    "tagname": "lb",
    "char_offset": 791,
    "page": "1.43",
    "token_offset": "Si[2]",
    "urn": "urn:cts:greekLit:tlg0057.tlg002.verbatim-lat1:2"
  },
  {
    "n": 5,
    "tagname": "lb",
    "char_offset": 858,
    "page": "1.43",
    "token_offset": "cognoscibile,[1]",
    "urn": "urn:cts:greekLit:tlg0057.tlg002.verbatim-lat1:2"
  },
  {
    "n": 6,
    "tagname": "lb",
    "char_offset": 913,
    "page": "1.43",
    "token_offset": "instrumenta;[1]",
    "urn": "urn:cts:greekLit:tlg0057.tlg002.verbatim-lat1:2"
  },
  {
    "n": 7,
    "tagname": "lb",
    "char_offset": 967,
    "page": "1.43",
    "token_offset": "discipulus[1]",
    "urn": "urn:cts:greekLit:tlg0057.tlg002.verbatim-lat1:2"
  },
  {
    "n": 8,
    "tagname": "lb",
    "char_offset": 1024,
    "page": "1.43",
    "token_offset": "partem[1]",
    "urn": "urn:cts:greekLit:tlg0057.tlg002.verbatim-lat1:2"
  },
  {
    "n": 9,
    "tagname": "lb",
    "char_offset": 1084,
    "page": "1.43",
    "token_offset": "ejusmodi[1]",
    "urn": "urn:cts:greekLit:tlg0057.tlg002.verbatim-lat1:2"
  },
  {
    "n": 10,
    "tagname": "lb",
    "char_offset": 1135,
    "page": "1.43",
    "token_offset": "quae[4]",
    "urn": "urn:cts:greekLit:tlg0057.tlg002.verbatim-lat1:2"
  },
  {
    "n": 11,
    "tagname": "lb",
    "char_offset": 1193,
    "page": "1.43",
    "token_offset": "perlegere,[1]",
    "urn": "urn:cts:greekLit:tlg0057.tlg002.verbatim-lat1:2"
  },
  {
    "n": 12,
    "tagname": "lb",
    "char_offset": 1246,
    "page": "1.43",
    "token_offset": "quid[1]",
    "urn": "urn:cts:greekLit:tlg0057.tlg002.verbatim-lat1:2"
  },
  {
    "n": 13,
    "tagname": "lb",
    "char_offset": 1301,
    "page": "1.43",
    "token_offset": "Stoicis[1]",
    "urn": "urn:cts:greekLit:tlg0057.tlg002.verbatim-lat1:2"
  },
  {
    "n": 14,
    "tagname": "lb",
    "char_offset": 1349,
    "page": "1.43",
    "token_offset": "et[5]",
    "urn": "urn:cts:greekLit:tlg0057.tlg002.verbatim-lat1:2"
  },
  {
    "n": 15,
    "tagname": "lb",
    "char_offset": 1407,
    "page": "1.43",
    "token_offset": "liceat;[1]",
    "urn": "urn:cts:greekLit:tlg0057.tlg002.verbatim-lat1:2"
  },
  {
    "n": 16,
    "tagname": "lb",
    "char_offset": 1464,
    "page": "1.43",
    "token_offset": "doctrinam[1]",
    "urn": "urn:cts:greekLit:tlg0057.tlg002.verbatim-lat1:2"
  },
  {
    "n": 17,
    "tagname": "lb",
    "char_offset": 1518,
    "page": "1.43",
    "token_offset": "enim[2]",
    "urn": "urn:cts:greekLit:tlg0057.tlg002.verbatim-lat1:2"
  },
  {
    "n": 18,
    "tagname": "lb",
    "char_offset": 1574,
    "page": "1.43",
    "token_offset": "instrumentum[1]",
    "urn": "urn:cts:greekLit:tlg0057.tlg002.verbatim-lat1:2"
  },
  {
    "n": "1.44",
    "tagname": "pb",
    "char_offset": 1626,
    "token_offset": "comparatione[1]",
    "urn": "urn:cts:greekLit:tlg0057.tlg002.verbatim-lat1:2"
  },
  {
    "n": 1,
    "tagname": "lb",
    "char_offset": 1626,
    "page": "1.44",
    "token_offset": "comparatione[1]",
    "urn": "urn:cts:greekLit:tlg0057.tlg002.verbatim-lat1:2"
  },
  {
    "n": 2,
    "tagname": "lb",
    "char_offset": 1675,
    "page": "1.44",
    "token_offset": "de[3]",
    "urn": "urn:cts:greekLit:tlg0057.tlg002.verbatim-lat1:2"
  },
  {
    "n": 3,
    "tagname": "lb",
    "char_offset": 1732,
    "page": "1.44",
    "token_offset": "anceps[1]",
    "urn": "urn:cts:greekLit:tlg0057.tlg002.verbatim-lat1:2"
  },
  {
    "n": 4,
    "tagname": "lb",
    "char_offset": 1782,
    "page": "1.44",
    "token_offset": "decet,[1]",
    "urn": "urn:cts:greekLit:tlg0057.tlg002.verbatim-lat1:2"
  },
  {
    "n": 5,
    "tagname": "lb",
    "char_offset": 1845,
    "page": "1.44",
    "token_offset": "inesse,[1]",
    "urn": "urn:cts:greekLit:tlg0057.tlg002.verbatim-lat1:2"
  },
  {
    "n": 6,
    "tagname": "lb",
    "char_offset": 1898,
    "page": "1.44",
    "token_offset": "utramque[2]",
    "urn": "urn:cts:greekLit:tlg0057.tlg002.verbatim-lat1:2"
  },
  {
    "n": 7,
    "tagname": "lb",
    "char_offset": 1948,
    "page": "1.44",
    "token_offset": "artifices[1]",
    "urn": "urn:cts:greekLit:tlg0057.tlg002.verbatim-lat1:2"
  },
  {
    "n": 8,
    "tagname": "lb",
    "char_offset": 2013,
    "page": "1.44",
    "token_offset": "argumentationem,[1]",
    "urn": "urn:cts:greekLit:tlg0057.tlg002.verbatim-lat1:2"
  },
  {
    "n": 9,
    "tagname": "lb",
    "char_offset": 2053,
    "page": "1.44",
    "token_offset": "computationem,[1]",
    "urn": "urn:cts:greekLit:tlg0057.tlg002.verbatim-lat1:2"
  },
  {
    "n": 10,
    "tagname": "lb",
    "char_offset": 2104,
    "page": "1.44",
    "token_offset": "attendere,[1]",
    "urn": "urn:cts:greekLit:tlg0057.tlg002.verbatim-lat1:2"
  },
  {
    "n": 11,
    "tagname": "lb",
    "char_offset": 2160,
    "page": "1.44",
    "token_offset": "Similiter[1]",
    "urn": "urn:cts:greekLit:tlg0057.tlg002.verbatim-lat1:2"
  },
  {
    "n": 12,
    "tagname": "lb",
    "char_offset": 2214,
    "page": "1.44",
    "token_offset": "et[9]",
    "urn": "urn:cts:greekLit:tlg0057.tlg002.verbatim-lat1:2"
  },
  {
    "n": 13,
    "tagname": "lb",
    "char_offset": 2271,
    "page": "1.44",
    "token_offset": "docent,[1]",
    "urn": "urn:cts:greekLit:tlg0057.tlg002.verbatim-lat1:2"
  },
  {
    "n": 14,
    "tagname": "lb",
    "char_offset": 2325,
    "page": "1.44",
    "token_offset": "discipuli[1]",
    "urn": "urn:cts:greekLit:tlg0057.tlg002.verbatim-lat1:2"
  },
  {
    "n": 15,
    "tagname": "lb",
    "char_offset": 2381,
    "page": "1.44",
    "token_offset": "sed[5]",
    "urn": "urn:cts:greekLit:tlg0057.tlg002.verbatim-lat1:2"
  },
  {
    "n": 16,
    "tagname": "lb",
    "char_offset": 2439,
    "page": "1.44",
    "token_offset": "edant[1]",
    "urn": "urn:cts:greekLit:tlg0057.tlg002.verbatim-lat1:2"
  },
  {
    "n": 17,
    "tagname": "lb",
    "char_offset": 2491,
    "page": "1.44",
    "token_offset": "enim[3]",
    "urn": "urn:cts:greekLit:tlg0057.tlg002.verbatim-lat1:2"
  },
  {
    "n": "1.45",
    "tagname": "pb",
    "char_offset": 2551,
    "token_offset": "afferunt,[1]",
    "urn": "urn:cts:greekLit:tlg0057.tlg002.verbatim-lat1:2"
  },
  {
    "n": 1,
    "tagname": "lb",
    "char_offset": 2551,
    "page": "1.45",
    "token_offset": "afferunt,[1]",
    "urn": "urn:cts:greekLit:tlg0057.tlg002.verbatim-lat1:2"
  },
  {
    "n": 2,
    "tagname": "lb",
    "char_offset": 2605,
    "page": "1.45",
    "token_offset": "cognoscuntur.[1]",
    "urn": "urn:cts:greekLit:tlg0057.tlg002.verbatim-lat1:2"
  },
  {
    "n": 3,
    "tagname": "lb",
    "char_offset": 2664,
    "page": "1.45",
    "token_offset": "evidentissimum,[1]",
    "urn": "urn:cts:greekLit:tlg0057.tlg002.verbatim-lat1:2"
  },
  {
    "n": 4,
    "tagname": "lb",
    "char_offset": 2711,
    "page": "1.45",
    "token_offset": "uni[1]",
    "urn": "urn:cts:greekLit:tlg0057.tlg002.verbatim-lat1:2"
  },
  {
    "n": 5,
    "tagname": "lb",
    "char_offset": 2762,
    "page": "1.45",
    "token_offset": "igitur[2]",
    "urn": "urn:cts:greekLit:tlg0057.tlg002.verbatim-lat1:2"
  },
  {
    "n": 6,
    "tagname": "lb",
    "char_offset": 2816,
    "page": "1.45",
    "token_offset": "quam[6]",
    "urn": "urn:cts:greekLit:tlg0057.tlg002.verbatim-lat1:2"
  },
  {
    "n": 7,
    "tagname": "lb",
    "char_offset": 2870,
    "page": "1.45",
    "token_offset": "apparent[1]",
    "urn": "urn:cts:greekLit:tlg0057.tlg002.verbatim-lat1:2"
  },
  {
    "n": 8,
    "tagname": "lb",
    "char_offset": 2922,
    "page": "1.45",
    "token_offset": "enim[4]",
    "urn": "urn:cts:greekLit:tlg0057.tlg002.verbatim-lat1:2"
  },
  {
    "n": 9,
    "tagname": "lb",
    "char_offset": 2981,
    "page": "1.45",
    "token_offset": "solutiones[1]",
    "urn": "urn:cts:greekLit:tlg0057.tlg002.verbatim-lat1:2"
  },
  {
    "n": 10,
    "tagname": "lb",
    "char_offset": 3032,
    "page": "1.45",
    "token_offset": "Academicorum[1]",
    "urn": "urn:cts:greekLit:tlg0057.tlg002.verbatim-lat1:2"
  },
  {
    "n": 11,
    "tagname": "lb",
    "char_offset": 3085,
    "page": "1.45",
    "token_offset": "saltem[1]",
    "urn": "urn:cts:greekLit:tlg0057.tlg002.verbatim-lat1:2"
  },
  {
    "n": 12,
    "tagname": "lb",
    "char_offset": 3146,
    "page": "1.45",
    "token_offset": "rationes,[2]",
    "urn": "urn:cts:greekLit:tlg0057.tlg002.verbatim-lat1:2"
  },
  {
    "n": 13,
    "tagname": "lb",
    "char_offset": 3191,
    "page": "1.45",
    "token_offset": "o[1]",
    "urn": "urn:cts:greekLit:tlg0057.tlg002.verbatim-lat1:2"
  },
  {
    "n": 14,
    "tagname": "lb",
    "char_offset": 3246,
    "page": "1.45",
    "token_offset": "improbe[1]",
    "urn": "urn:cts:greekLit:tlg0057.tlg002.verbatim-lat1:2"
  },
  {
    "n": 15,
    "tagname": "lb",
    "char_offset": 3296,
    "page": "1.45",
    "token_offset": "quales[1]",
    "urn": "urn:cts:greekLit:tlg0057.tlg002.verbatim-lat1:2"
  },
  {
    "type": "textpart",
    "subtype": "chapter",
    "n": "2",
    "content": "Cap. II. Ego vero nihil aliud comprehensibile puto significare, quam cognoscibile; neque aliud comprehendere, quam certo cognoscere; similem vero his dici comprehensionem et comprehensivam imaginationem. Cum enim quaedam putamus vel videre, vel audire, vel omnino sentire, quemadmodum in somniis et deliriis; quaedam vero non arbitramur solum, sed revera videmus, vel omnino sensa percipimus: haec quidem posteriora omnes homines, praeter Academicos ac Pyrrhonios, ad certam cognitionem venire credunt; quae vero per somnia, aut quae delirantium fingit animus, falsa esse haec omnia. Si autem sic rem se habere concedant, deleant ea, quae sunt in libris, in quibus scribunt, neque sapientem insano, neque sanum aegro, neque vigilantem dormiente, fide digniorem ad rerum cognitionem esse. Si vero nihil magis ipsis, quam contrario modo affectis cognoscibile, confusa sunt certe cognoscendae veritatis instrumenta; neque ipse praeceptor Academicus, nec ejus discipulus poterit judicare de rationibus dictis in utramque partem oppositorum. Praeterea non indigebimus a principio ejusmodi praeceptoribus, cum et ipsi possimus scripta, quae a sectarum auctoribus sunt ex opposito divisa, perlegere, nec minus quam ipsi Academici dignoscere; et si quid ipsorum obscurum sit, id quod apud Chrysippum, Stoicis praeceptoribus; quod autem apud Theophrastum et Aristotelem, ipsis Peripateticis certius nominare liceat; et sic de caeteris, ita ut nihil Academicis ad doctrinam sit reliquum juxta Favorini rationem. Senioribus enim hoc erat praeceptum, nullum esse judicandi instrumentum homini concessum a natura, quo cuncta, comparatione facta, accurate cognosceret. Quapropter nihil de ulla re volebant affirmare, sed de omnibus semper anceps ferre judicium. Sed si nobis concedant, ut decet, naturalibus judicandi instrumentis sensum sufficienter inesse, nulla jam nobis opus erit argumentatione in utramque partem, sed alia quadam repetitione, ut artifices non statim artem discipulis praebent, sed aliam argumentationem, a multis dictam calculis computationem, hoc est, praeesse ei, qui exercetur, et attendere, in quibus hic fallitur, eaque sola corrigere. Similiter et puerorum gubernator luctantium errores emendat, et grammaticus et rhetor et geometra et musicus sic docent, non labefactantes, neque convellentes, quam discipuli fidem habent de naturalibus instrumentis judicandi, sed ipsis exercendis praefecti, donec singulas actiones edant inculpatas; non vero ad epochen adducunt. Ipsi enim sunt, qui in actionibus cum sensibus diffidentiam afferunt, vel ea contemnunt, quae ab aliquo certo cognoscuntur. Carneades igitur neque id, quod est omnium evidentissimum, credendum esse concedit, quod magnitudines uni aequales sunt et aequales inter se. Habemus igitur rationes, quibus haec solvere contendit, et alia quam plurima eorum, quae evidenter exsistere tibi apparent ac creduntur, adhuc ad id conservatas. Ab ejus enim discipulis collectae scriptis mandatae fuerunt; solutiones vero neque ab ipsis, nec ab ullo alio Academicorum post eum allatae sunt. Igitur si nihil aliud, saltem hoc unum demonstravit, quod fallaces ejusmodi sint rationes, et quaerendam esse nobis harum solutionem, o discipuli. Improbum illud est, nec tamen minus improbe fecerunt, qui has scripsere rationes, nec, quales essent, nobis indicarunt.",
    "line": 16,
    "page": "1.45",
    "tokens": [
      "Cap.",
      "II.",
      "Ego",
      "vero",
      "nihil",
      "aliud",
      "comprehensibile",
      "puto",
      "significare,",
      "quam",
      "cognoscibile;",
      "neque",
      "aliud",
      "comprehendere,",
      "quam",
      "certo",
      "cognoscere;",
      "similem",
      "vero",
      "his",
      "dici",
      "comprehensionem",
      "et",
      "comprehensivam",
      "imaginationem.",
      "Cum",
      "enim",
      "quaedam",
      "putamus",
      "vel",
      "videre,",
      "vel",
      "audire,",
      "vel",
      "omnino",
      "sentire,",
      "quemadmodum",
      "in",
      "somniis",
      "et",
      "deliriis;",
      "quaedam",
      "vero",
      "non",
      "arbitramur",
      "solum,",
      "sed",
      "revera",
      "videmus,",
      "vel",
      "omnino",
      "sensa",
      "percipimus:",
      "haec",
      "quidem",
      "posteriora",
      "omnes",
      "homines,",
      "praeter",
      "Academicos",
      "ac",
      "Pyrrhonios,",
      "ad",
      "certam",
      "cognitionem",
      "venire",
      "credunt;",
      "quae",
      "vero",
      "per",
      "somnia,",
      "aut",
      "quae",
      "delirantium",
      "fingit",
      "animus,",
      "falsa",
      "esse",
      "haec",
      "omnia.",
      "Si",
      "autem",
      "sic",
      "rem",
      "se",
      "habere",
      "concedant,",
      "deleant",
      "ea,",
      "quae",
      "sunt",
      "in",
      "libris,",
      "in",
      "quibus",
      "scribunt,",
      "neque",
      "sapientem",
      "insano,",
      "neque",
      "sanum",
      "aegro,",
      "neque",
      "vigilantem",
      "dormiente,",
      "fide",
      "digniorem",
      "ad",
      "rerum",
      "cognitionem",
      "esse.",
      "Si",
      "vero",
      "nihil",
      "magis",
      "ipsis,",
      "quam",
      "contrario",
      "modo",
      "affectis",
      "cognoscibile,",
      "confusa",
      "sunt",
      "certe",
      "cognoscendae",
      "veritatis",
      "instrumenta;",
      "neque",
      "ipse",
      "praeceptor",
      "Academicus,",
      "nec",
      "ejus",
      "discipulus",
      "poterit",
      "judicare",
      "de",
      "rationibus",
      "dictis",
      "in",
      "utramque",
      "partem",
      "oppositorum.",
      "Praeterea",
      "non",
      "indigebimus",
      "a",
      "principio",
      "ejusmodi",
      "praeceptoribus,",
      "cum",
      "et",
      "ipsi",
      "possimus",
      "scripta,",
      "quae",
      "a",
      "sectarum",
      "auctoribus",
      "sunt",
      "ex",
      "opposito",
      "divisa,",
      "perlegere,",
      "nec",
      "minus",
      "quam",
      "ipsi",
      "Academici",
      "dignoscere;",
      "et",
      "si",
      "quid",
      "ipsorum",
      "obscurum",
      "sit,",
      "id",
      "quod",
      "apud",
      "Chrysippum,",
      "Stoicis",
      "praeceptoribus;",
      "quod",
      "autem",
      "apud",
      "Theophrastum",
      "et",
      "Aristotelem,",
      "ipsis",
      "Peripateticis",
      "certius",
      "nominare",
      "liceat;",
      "et",
      "sic",
      "de",
      "caeteris,",
      "ita",
      "ut",
      "nihil",
      "Academicis",
      "ad",
      "doctrinam",
      "sit",
      "reliquum",
      "juxta",
      "Favorini",
      "rationem.",
      "Senioribus",
      "enim",
      "hoc",
      "erat",
      "praeceptum,",
      "nullum",
      "esse",
      "judicandi",
      "instrumentum",
      "homini",
      "concessum",
      "a",
      "natura,",
      "quo",
      "cuncta,",
      "comparatione",
      "facta,",
      "accurate",
      "cognosceret.",
      "Quapropter",
      "nihil",
      "de",
      "ulla",
      "re",
      "volebant",
      "affirmare,",
      "sed",
      "de",
      "omnibus",
      "semper",
      "anceps",
      "ferre",
      "judicium.",
      "Sed",
      "si",
      "nobis",
      "concedant,",
      "ut",
      "decet,",
      "naturalibus",
      "judicandi",
      "instrumentis",
      "sensum",
      "sufficienter",
      "inesse,",
      "nulla",
      "jam",
      "nobis",
      "opus",
      "erit",
      "argumentatione",
      "in",
      "utramque",
      "partem,",
      "sed",
      "alia",
      "quadam",
      "repetitione,",
      "ut",
      "artifices",
      "non",
      "statim",
      "artem",
      "discipulis",
      "praebent,",
      "sed",
      "aliam",
      "argumentationem,",
      "a",
      "multis",
      "dictam",
      "calculis",
      "computationem,",
      "hoc",
      "est,",
      "praeesse",
      "ei,",
      "qui",
      "exercetur,",
      "et",
      "attendere,",
      "in",
      "quibus",
      "hic",
      "fallitur,",
      "eaque",
      "sola",
      "corrigere.",
      "Similiter",
      "et",
      "puerorum",
      "gubernator",
      "luctantium",
      "errores",
      "emendat,",
      "et",
      "grammaticus",
      "et",
      "rhetor",
      "et",
      "geometra",
      "et",
      "musicus",
      "sic",
      "docent,",
      "non",
      "labefactantes,",
      "neque",
      "convellentes,",
      "quam",
      "discipuli",
      "fidem",
      "habent",
      "de",
      "naturalibus",
      "instrumentis",
      "judicandi,",
      "sed",
      "ipsis",
      "exercendis",
      "praefecti,",
      "donec",
      "singulas",
      "actiones",
      "edant",
      "inculpatas;",
      "non",
      "vero",
      "ad",
      "epochen",
      "adducunt.",
      "Ipsi",
      "enim",
      "sunt,",
      "qui",
      "in",
      "actionibus",
      "cum",
      "sensibus",
      "diffidentiam",
      "afferunt,",
      "vel",
      "ea",
      "contemnunt,",
      "quae",
      "ab",
      "aliquo",
      "certo",
      "cognoscuntur.",
      "Carneades",
      "igitur",
      "neque",
      "id,",
      "quod",
      "est",
      "omnium",
      "evidentissimum,",
      "credendum",
      "esse",
      "concedit,",
      "quod",
      "magnitudines",
      "uni",
      "aequales",
      "sunt",
      "et",
      "aequales",
      "inter",
      "se.",
      "Habemus",
      "igitur",
      "rationes,",
      "quibus",
      "haec",
      "solvere",
      "contendit,",
      "et",
      "alia",
      "quam",
      "plurima",
      "eorum,",
      "quae",
      "evidenter",
      "exsistere",
      "tibi",
      "apparent",
      "ac",
      "creduntur,",
      "adhuc",
      "ad",
      "id",
      "conservatas.",
      "Ab",
      "ejus",
      "enim",
      "discipulis",
      "collectae",
      "scriptis",
      "mandatae",
      "fuerunt;",
      "solutiones",
      "vero",
      "neque",
      "ab",
      "ipsis,",
      "nec",
      "ab",
      "ullo",
      "alio",
      "Academicorum",
      "post",
      "eum",
      "allatae",
      "sunt.",
      "Igitur",
      "si",
      "nihil",
      "aliud,",
      "saltem",
      "hoc",
      "unum",
      "demonstravit,",
      "quod",
      "fallaces",
      "ejusmodi",
      "sint",
      "rationes,",
      "et",
      "quaerendam",
      "esse",
      "nobis",
      "harum",
      "solutionem,",
      "o",
      "discipuli.",
      "Improbum",
      "illud",
      "est,",
      "nec",
      "tamen",
      "minus",
      "improbe",
      "fecerunt,",
      "qui",
      "has",
      "scripsere",
      "rationes,",
      "nec,",
      "quales",
      "essent,",
      "nobis",
      "indicarunt."
    ],
    "urn": "urn:cts:greekLit:tlg0057.tlg002.verbatim-lat1:2"
  },
  {
    "n": 16,
    "tagname": "lb",
    "char_offset": 0,
    "page": "1.45",
    "token_offset": null,
    "urn": "urn:cts:greekLit:tlg0057.tlg002.verbatim-lat1:3"
  },
  {
    "rend": "indent",
    "tagname": "p",
    "char_offset": 0,
    "line": 16,
    "page": "1.45",
    "token_offset": null,
    "urn": "urn:cts:greekLit:tlg0057.tlg002.verbatim-lat1:3",
    "end_char_offset": 0,
    "end_token_offset": null
  },
  {
    "value": "3",
    "tagname": "num",
    "char_offset": 0,
    "line": 17,
    "page": "1.45",
    "token_offset": null,
    "urn": "urn:cts:greekLit:tlg0057.tlg002.verbatim-lat1:3",
    "end_char_offset": 10,
    "end_token_offset": "III.[1]"
  },
  {
    "type": "head",
    "tagname": "label",
    "char_offset": 0,
    "line": 17,
    "page": "1.45",
    "token_offset": null,
    "urn": "urn:cts:greekLit:tlg0057.tlg002.verbatim-lat1:3",
    "end_char_offset": 10,
    "end_token_offset": "III.[1]"
  },
  {
    "n": 17,
    "tagname": "lb",
    "char_offset": 52,
    "page": "1.45",
    "token_offset": "adesset,[1]",
    "urn": "urn:cts:greekLit:tlg0057.tlg002.verbatim-lat1:3"
  },
  {
    "n": 18,
    "tagname": "lb",
    "char_offset": 107,
    "page": "1.45",
    "token_offset": "praebere,[1]",
    "urn": "urn:cts:greekLit:tlg0057.tlg002.verbatim-lat1:3"
  },
  {
    "n": "1.46",
    "tagname": "pb",
    "char_offset": 159,
    "token_offset": "unum[1]",
    "urn": "urn:cts:greekLit:tlg0057.tlg002.verbatim-lat1:3"
  },
  {
    "n": 1,
    "tagname": "lb",
    "char_offset": 159,
    "page": "1.46",
    "token_offset": "unum[1]",
    "urn": "urn:cts:greekLit:tlg0057.tlg002.verbatim-lat1:3"
  },
  {
    "n": 2,
    "tagname": "lb",
    "char_offset": 213,
    "page": "1.46",
    "token_offset": "in[1]",
    "urn": "urn:cts:greekLit:tlg0057.tlg002.verbatim-lat1:3"
  },
  {
    "n": 3,
    "tagname": "lb",
    "char_offset": 268,
    "page": "1.46",
    "token_offset": "sit[1]",
    "urn": "urn:cts:greekLit:tlg0057.tlg002.verbatim-lat1:3"
  },
  {
    "n": 4,
    "tagname": "lb",
    "char_offset": 337,
    "page": "1.46",
    "token_offset": "artificiosa[1]",
    "urn": "urn:cts:greekLit:tlg0057.tlg002.verbatim-lat1:3"
  },
  {
    "n": 5,
    "tagname": "lb",
    "char_offset": 382,
    "page": "1.46",
    "token_offset": "natura,[1]",
    "urn": "urn:cts:greekLit:tlg0057.tlg002.verbatim-lat1:3"
  },
  {
    "n": 6,
    "tagname": "lb",
    "char_offset": 436,
    "page": "1.46",
    "token_offset": "iisdem[1]",
    "urn": "urn:cts:greekLit:tlg0057.tlg002.verbatim-lat1:3"
  },
  {
    "n": 7,
    "tagname": "lb",
    "char_offset": 492,
    "page": "1.46",
    "token_offset": "ipsam[1]",
    "urn": "urn:cts:greekLit:tlg0057.tlg002.verbatim-lat1:3"
  },
  {
    "n": 8,
    "tagname": "lb",
    "char_offset": 547,
    "page": "1.46",
    "token_offset": "ipsos[1]",
    "urn": "urn:cts:greekLit:tlg0057.tlg002.verbatim-lat1:3"
  },
  {
    "n": 9,
    "tagname": "lb",
    "char_offset": 602,
    "page": "1.46",
    "token_offset": "exercere;[1]",
    "urn": "urn:cts:greekLit:tlg0057.tlg002.verbatim-lat1:3"
  },
  {
    "n": 10,
    "tagname": "lb",
    "char_offset": 672,
    "page": "1.46",
    "token_offset": "aedificatoriam,[1]",
    "urn": "urn:cts:greekLit:tlg0057.tlg002.verbatim-lat1:3"
  },
  {
    "n": 11,
    "tagname": "lb",
    "char_offset": 724,
    "page": "1.46",
    "token_offset": "legendi,[1]",
    "urn": "urn:cts:greekLit:tlg0057.tlg002.verbatim-lat1:3"
  },
  {
    "n": 12,
    "tagname": "lb",
    "char_offset": 775,
    "page": "1.46",
    "token_offset": "artem[2]",
    "urn": "urn:cts:greekLit:tlg0057.tlg002.verbatim-lat1:3"
  },
  {
    "n": 13,
    "tagname": "lb",
    "char_offset": 835,
    "page": "1.46",
    "token_offset": "sit[4]",
    "urn": "urn:cts:greekLit:tlg0057.tlg002.verbatim-lat1:3"
  },
  {
    "n": 14,
    "tagname": "lb",
    "char_offset": 887,
    "page": "1.46",
    "token_offset": "ea[1]",
    "urn": "urn:cts:greekLit:tlg0057.tlg002.verbatim-lat1:3"
  },
  {
    "n": 15,
    "tagname": "lb",
    "char_offset": 945,
    "page": "1.46",
    "token_offset": "exercere,[1]",
    "urn": "urn:cts:greekLit:tlg0057.tlg002.verbatim-lat1:3"
  },
  {
    "n": 16,
    "tagname": "lb",
    "char_offset": 992,
    "page": "1.46",
    "token_offset": "in[2]",
    "urn": "urn:cts:greekLit:tlg0057.tlg002.verbatim-lat1:3"
  },
  {
    "n": 17,
    "tagname": "lb",
    "char_offset": 1054,
    "page": "1.46",
    "token_offset": "supervacaneum[1]",
    "urn": "urn:cts:greekLit:tlg0057.tlg002.verbatim-lat1:3"
  },
  {
    "n": 18,
    "tagname": "lb",
    "char_offset": 1102,
    "page": "1.46",
    "token_offset": "dicta[1]",
    "urn": "urn:cts:greekLit:tlg0057.tlg002.verbatim-lat1:3"
  },
  {
    "n": 19,
    "tagname": "lb",
    "char_offset": 1160,
    "page": "1.46",
    "token_offset": "doctores.[1]",
    "urn": "urn:cts:greekLit:tlg0057.tlg002.verbatim-lat1:3"
  },
  {
    "n": "1.47",
    "tagname": "pb",
    "char_offset": 1210,
    "token_offset": "scripserit,[2]",
    "urn": "urn:cts:greekLit:tlg0057.tlg002.verbatim-lat1:3"
  },
  {
    "n": 1,
    "tagname": "lb",
    "char_offset": 1210,
    "page": "1.47",
    "token_offset": "scripserit,[2]",
    "urn": "urn:cts:greekLit:tlg0057.tlg002.verbatim-lat1:3"
  },
  {
    "n": 2,
    "tagname": "lb",
    "char_offset": 1268,
    "page": "1.47",
    "token_offset": "faber[1]",
    "urn": "urn:cts:greekLit:tlg0057.tlg002.verbatim-lat1:3"
  },
  {
    "n": 3,
    "tagname": "lb",
    "char_offset": 1323,
    "page": "1.47",
    "token_offset": "extendat,[1]",
    "urn": "urn:cts:greekLit:tlg0057.tlg002.verbatim-lat1:3"
  },
  {
    "n": 4,
    "tagname": "lb",
    "char_offset": 1372,
    "page": "1.47",
    "token_offset": "cubitum,[1]",
    "urn": "urn:cts:greekLit:tlg0057.tlg002.verbatim-lat1:3"
  },
  {
    "n": 5,
    "tagname": "lb",
    "char_offset": 1432,
    "page": "1.47",
    "token_offset": "inquit,[1]",
    "urn": "urn:cts:greekLit:tlg0057.tlg002.verbatim-lat1:3"
  },
  {
    "n": 6,
    "tagname": "lb",
    "char_offset": 1485,
    "page": "1.47",
    "token_offset": "igitur[2]",
    "urn": "urn:cts:greekLit:tlg0057.tlg002.verbatim-lat1:3"
  },
  {
    "n": 7,
    "tagname": "lb",
    "char_offset": 1537,
    "page": "1.47",
    "token_offset": "aut[4]",
    "urn": "urn:cts:greekLit:tlg0057.tlg002.verbatim-lat1:3"
  },
  {
    "n": 8,
    "tagname": "lb",
    "char_offset": 1592,
    "page": "1.47",
    "token_offset": "nec[2]",
    "urn": "urn:cts:greekLit:tlg0057.tlg002.verbatim-lat1:3"
  },
  {
    "n": 9,
    "tagname": "lb",
    "char_offset": 1648,
    "page": "1.47",
    "token_offset": "exerces[1]",
    "urn": "urn:cts:greekLit:tlg0057.tlg002.verbatim-lat1:3"
  },
  {
    "n": 10,
    "tagname": "lb",
    "char_offset": 1702,
    "page": "1.47",
    "token_offset": "nihil[2]",
    "urn": "urn:cts:greekLit:tlg0057.tlg002.verbatim-lat1:3"
  },
  {
    "n": 11,
    "tagname": "lb",
    "char_offset": 1759,
    "page": "1.47",
    "token_offset": "Neque[1]",
    "urn": "urn:cts:greekLit:tlg0057.tlg002.verbatim-lat1:3"
  },
  {
    "n": 12,
    "tagname": "lb",
    "char_offset": 1816,
    "page": "1.47",
    "token_offset": "quaedam[2]",
    "urn": "urn:cts:greekLit:tlg0057.tlg002.verbatim-lat1:3"
  },
  {
    "n": 13,
    "tagname": "lb",
    "char_offset": 1872,
    "page": "1.47",
    "token_offset": "inveniendae[1]",
    "urn": "urn:cts:greekLit:tlg0057.tlg002.verbatim-lat1:3"
  },
  {
    "n": 14,
    "tagname": "lb",
    "char_offset": 1919,
    "page": "1.47",
    "token_offset": "falsi[1]",
    "urn": "urn:cts:greekLit:tlg0057.tlg002.verbatim-lat1:3"
  },
  {
    "n": 15,
    "tagname": "lb",
    "char_offset": 1972,
    "page": "1.47",
    "token_offset": "cognitio.[1]",
    "urn": "urn:cts:greekLit:tlg0057.tlg002.verbatim-lat1:3"
  },
  {
    "n": 16,
    "tagname": "lb",
    "char_offset": 2027,
    "page": "1.47",
    "token_offset": "natura[2]",
    "urn": "urn:cts:greekLit:tlg0057.tlg002.verbatim-lat1:3"
  },
  {
    "n": 17,
    "tagname": "lb",
    "char_offset": 2080,
    "page": "1.47",
    "token_offset": "certe[1]",
    "urn": "urn:cts:greekLit:tlg0057.tlg002.verbatim-lat1:3"
  },
  {
    "n": 18,
    "tagname": "lb",
    "char_offset": 2137,
    "page": "1.47",
    "token_offset": "dicit,[1]",
    "urn": "urn:cts:greekLit:tlg0057.tlg002.verbatim-lat1:3"
  },
  {
    "n": 19,
    "tagname": "lb",
    "char_offset": 2198,
    "page": "1.47",
    "token_offset": "instrumenta,[1]",
    "urn": "urn:cts:greekLit:tlg0057.tlg002.verbatim-lat1:3"
  },
  {
    "n": "1.48",
    "tagname": "pb",
    "char_offset": 2243,
    "token_offset": "inani[1]",
    "urn": "urn:cts:greekLit:tlg0057.tlg002.verbatim-lat1:3"
  },
  {
    "n": 1,
    "tagname": "lb",
    "char_offset": 2243,
    "page": "1.48",
    "token_offset": "inani[1]",
    "urn": "urn:cts:greekLit:tlg0057.tlg002.verbatim-lat1:3"
  },
  {
    "n": 2,
    "tagname": "lb",
    "char_offset": 2291,
    "page": "1.48",
    "token_offset": "spem[1]",
    "urn": "urn:cts:greekLit:tlg0057.tlg002.verbatim-lat1:3"
  },
  {
    "n": 3,
    "tagname": "lb",
    "char_offset": 2351,
    "page": "1.48",
    "token_offset": "Conspicuus[1]",
    "urn": "urn:cts:greekLit:tlg0057.tlg002.verbatim-lat1:3"
  },
  {
    "n": 4,
    "tagname": "lb",
    "char_offset": 2395,
    "page": "1.48",
    "token_offset": "omnia[1]",
    "urn": "urn:cts:greekLit:tlg0057.tlg002.verbatim-lat1:3"
  },
  {
    "n": 5,
    "tagname": "lb",
    "char_offset": 2449,
    "page": "1.48",
    "token_offset": "ea,[1]",
    "urn": "urn:cts:greekLit:tlg0057.tlg002.verbatim-lat1:3"
  },
  {
    "n": 6,
    "tagname": "lb",
    "char_offset": 2502,
    "page": "1.48",
    "token_offset": "simulans[1]",
    "urn": "urn:cts:greekLit:tlg0057.tlg002.verbatim-lat1:3"
  },
  {
    "n": 7,
    "tagname": "lb",
    "char_offset": 2563,
    "page": "1.48",
    "token_offset": "illi,[1]",
    "urn": "urn:cts:greekLit:tlg0057.tlg002.verbatim-lat1:3"
  },
  {
    "type": "textpart",
    "subtype": "chapter",
    "n": "3",
    "content": "Cap. III. Libenter quaererem, si Favorinus adesset, an jubeat omnibus his rationibus assensum me praebere, vel considerare, utrum verae sint, vel falsae; unum enim considerandum esse concessit. Quaererem autem in universum, num a natura singulis hominibus insitum sit discernere veras rationes a falsis; vel sit aliqua ratio artificiosa ad utrarumque cognitionem. Si enim a natura, quidni omnes inter nos consentimus et eadem de iisdem rebus pronunciamus? Si vero sit quaedam methodus, ipsam primo oportuit addiscere, deinde ludo praefectos ipsos discipulos vario modo, exemplis quamplurimis exercere; ut eos, qui luctandi artem discunt, vel sutoriam, vel aedificatoriam, vel naves compingendi, vel rhetoricam, vel legendi, vel scribendi, vel alio quotis modo secundum artem operari. Si igitur quispiam Academicus scripserit, quid sit demonstratio, quid sophisma, et quomodo oporteat ea dignoscere, et quemadmodum circa ea sese deceat exercere, ut Favorinus permittit judicium discipulis, in utramque partem disputantibus, nisi cum aliquid supervacaneum fuerit; docuerit Academicus singula, quae dicta sunt: nos vero habemus singularum praeceptionum doctores. Si vero nullus de ipsorum differentia scripserit, aut exercitationem formaverit, simile quid agit, ac faber praecipiens discipulo, ut metiatur, dirigat, extendat, ac circulum describat, nec illi praebet cubitum, libram, regulam, aut circinum. Sed nihil fortassis, inquit, in philosophia et praeceptis inest simile. Ne igitur assimules te aliquid cognoscere, aut enunciare, aut discedere ab allata a veteribus Academicis epoche, nec te jactes, dum grammatici opus perficis, qui te exerces in iis, quae antiqui dixerunt. Apud ipsos autem nihil esse praeclari manifestissimum est animadvertenti. Neque enim id proprium praeceptoris est, sed nugacitas quaedam et deliramentum. Unde igitur spes veritatis inveniendae relinquitur? Cui enim nullum est veri et falsi judicandi instrumentum, ejus est insperata cognitio. Aggredere autem solum sophistas docere, nobis a natura nullum insitum esse judicandi instrumentum, ut certe postea audacter asseverasti. Nobis autem fortasse dicit, sensum et intellectum certa esse veri judicandi instrumenta, quod quis concederet in logicis volens inani quadam spe volutari. Quicumque autem omnem spem sustulerunt, quemadmodum ipse, frustra nugantur. Conspicuus igitur est Favorinus, quem pudet, dum omnia subvertit, et fatetur se ignorare, unde orta sint ea, quae veteres Academici et Pyrrhonii dixere, simulans discipulis se judicium permittere, quod nec sibi ipsis illi, qui ante ipsum fuere, permiserunt.",
    "line": 8,
    "page": "1.48",
    "tokens": [
      "Cap.",
      "III.",
      "Libenter",
      "quaererem,",
      "si",
      "Favorinus",
      "adesset,",
      "an",
      "jubeat",
      "omnibus",
      "his",
      "rationibus",
      "assensum",
      "me",
      "praebere,",
      "vel",
      "considerare,",
      "utrum",
      "verae",
      "sint,",
      "vel",
      "falsae;",
      "unum",
      "enim",
      "considerandum",
      "esse",
      "concessit.",
      "Quaererem",
      "autem",
      "in",
      "universum,",
      "num",
      "a",
      "natura",
      "singulis",
      "hominibus",
      "insitum",
      "sit",
      "discernere",
      "veras",
      "rationes",
      "a",
      "falsis;",
      "vel",
      "sit",
      "aliqua",
      "ratio",
      "artificiosa",
      "ad",
      "utrarumque",
      "cognitionem.",
      "Si",
      "enim",
      "a",
      "natura,",
      "quidni",
      "omnes",
      "inter",
      "nos",
      "consentimus",
      "et",
      "eadem",
      "de",
      "iisdem",
      "rebus",
      "pronunciamus?",
      "Si",
      "vero",
      "sit",
      "quaedam",
      "methodus,",
      "ipsam",
      "primo",
      "oportuit",
      "addiscere,",
      "deinde",
      "ludo",
      "praefectos",
      "ipsos",
      "discipulos",
      "vario",
      "modo,",
      "exemplis",
      "quamplurimis",
      "exercere;",
      "ut",
      "eos,",
      "qui",
      "luctandi",
      "artem",
      "discunt,",
      "vel",
      "sutoriam,",
      "vel",
      "aedificatoriam,",
      "vel",
      "naves",
      "compingendi,",
      "vel",
      "rhetoricam,",
      "vel",
      "legendi,",
      "vel",
      "scribendi,",
      "vel",
      "alio",
      "quotis",
      "modo",
      "secundum",
      "artem",
      "operari.",
      "Si",
      "igitur",
      "quispiam",
      "Academicus",
      "scripserit,",
      "quid",
      "sit",
      "demonstratio,",
      "quid",
      "sophisma,",
      "et",
      "quomodo",
      "oporteat",
      "ea",
      "dignoscere,",
      "et",
      "quemadmodum",
      "circa",
      "ea",
      "sese",
      "deceat",
      "exercere,",
      "ut",
      "Favorinus",
      "permittit",
      "judicium",
      "discipulis,",
      "in",
      "utramque",
      "partem",
      "disputantibus,",
      "nisi",
      "cum",
      "aliquid",
      "supervacaneum",
      "fuerit;",
      "docuerit",
      "Academicus",
      "singula,",
      "quae",
      "dicta",
      "sunt:",
      "nos",
      "vero",
      "habemus",
      "singularum",
      "praeceptionum",
      "doctores.",
      "Si",
      "vero",
      "nullus",
      "de",
      "ipsorum",
      "differentia",
      "scripserit,",
      "aut",
      "exercitationem",
      "formaverit,",
      "simile",
      "quid",
      "agit,",
      "ac",
      "faber",
      "praecipiens",
      "discipulo,",
      "ut",
      "metiatur,",
      "dirigat,",
      "extendat,",
      "ac",
      "circulum",
      "describat,",
      "nec",
      "illi",
      "praebet",
      "cubitum,",
      "libram,",
      "regulam,",
      "aut",
      "circinum.",
      "Sed",
      "nihil",
      "fortassis,",
      "inquit,",
      "in",
      "philosophia",
      "et",
      "praeceptis",
      "inest",
      "simile.",
      "Ne",
      "igitur",
      "assimules",
      "te",
      "aliquid",
      "cognoscere,",
      "aut",
      "enunciare,",
      "aut",
      "discedere",
      "ab",
      "allata",
      "a",
      "veteribus",
      "Academicis",
      "epoche,",
      "nec",
      "te",
      "jactes,",
      "dum",
      "grammatici",
      "opus",
      "perficis,",
      "qui",
      "te",
      "exerces",
      "in",
      "iis,",
      "quae",
      "antiqui",
      "dixerunt.",
      "Apud",
      "ipsos",
      "autem",
      "nihil",
      "esse",
      "praeclari",
      "manifestissimum",
      "est",
      "animadvertenti.",
      "Neque",
      "enim",
      "id",
      "proprium",
      "praeceptoris",
      "est,",
      "sed",
      "nugacitas",
      "quaedam",
      "et",
      "deliramentum.",
      "Unde",
      "igitur",
      "spes",
      "veritatis",
      "inveniendae",
      "relinquitur?",
      "Cui",
      "enim",
      "nullum",
      "est",
      "veri",
      "et",
      "falsi",
      "judicandi",
      "instrumentum,",
      "ejus",
      "est",
      "insperata",
      "cognitio.",
      "Aggredere",
      "autem",
      "solum",
      "sophistas",
      "docere,",
      "nobis",
      "a",
      "natura",
      "nullum",
      "insitum",
      "esse",
      "judicandi",
      "instrumentum,",
      "ut",
      "certe",
      "postea",
      "audacter",
      "asseverasti.",
      "Nobis",
      "autem",
      "fortasse",
      "dicit,",
      "sensum",
      "et",
      "intellectum",
      "certa",
      "esse",
      "veri",
      "judicandi",
      "instrumenta,",
      "quod",
      "quis",
      "concederet",
      "in",
      "logicis",
      "volens",
      "inani",
      "quadam",
      "spe",
      "volutari.",
      "Quicumque",
      "autem",
      "omnem",
      "spem",
      "sustulerunt,",
      "quemadmodum",
      "ipse,",
      "frustra",
      "nugantur.",
      "Conspicuus",
      "igitur",
      "est",
      "Favorinus,",
      "quem",
      "pudet,",
      "dum",
      "omnia",
      "subvertit,",
      "et",
      "fatetur",
      "se",
      "ignorare,",
      "unde",
      "orta",
      "sint",
      "ea,",
      "quae",
      "veteres",
      "Academici",
      "et",
      "Pyrrhonii",
      "dixere,",
      "simulans",
      "discipulis",
      "se",
      "judicium",
      "permittere,",
      "quod",
      "nec",
      "sibi",
      "ipsis",
      "illi,",
      "qui",
      "ante",
      "ipsum",
      "fuere,",
      "permiserunt."
    ],
    "urn": "urn:cts:greekLit:tlg0057.tlg002.verbatim-lat1:3"
  },
  {
    "n": 8,
    "tagname": "lb",
    "char_offset": 0,
    "page": "1.48",
    "token_offset": null,
    "urn": "urn:cts:greekLit:tlg0057.tlg002.verbatim-lat1:4"
  },
  {
    "rend": "indent",
    "tagname": "p",
    "char_offset": 0,
    "line": 8,
    "page": "1.48",
    "token_offset": null,
    "urn": "urn:cts:greekLit:tlg0057.tlg002.verbatim-lat1:4",
    "end_char_offset": 0,
    "end_token_offset": null
  },
  {
    "value": "4",
    "tagname": "num",
    "char_offset": 0,
    "line": 9,
    "page": "1.48",
    "token_offset": null,
    "urn": "urn:cts:greekLit:tlg0057.tlg002.verbatim-lat1:4",
    "end_char_offset": 9,
    "end_token_offset": "IV.[1]"
  },
  {
    "type": "head",
    "tagname": "label",
    "char_offset": 0,
    "line": 9,
    "page": "1.48",
    "token_offset": null,
    "urn": "urn:cts:greekLit:tlg0057.tlg002.verbatim-lat1:4",
    "end_char_offset": 9,
    "end_token_offset": "IV.[1]"
  },
  {
    "n": 9,
    "tagname": "lb",
    "char_offset": 53,
    "page": "1.48",
    "token_offset": "aliquid[1]",
    "urn": "urn:cts:greekLit:tlg0057.tlg002.verbatim-lat1:4"
  },
  {
    "n": 10,
    "tagname": "lb",
    "char_offset": 103,
    "page": "1.48",
    "token_offset": "solum[1]",
    "urn": "urn:cts:greekLit:tlg0057.tlg002.verbatim-lat1:4"
  },
  {
    "n": 11,
    "tagname": "lb",
    "char_offset": 158,
    "page": "1.48",
    "token_offset": "esse,[1]",
    "urn": "urn:cts:greekLit:tlg0057.tlg002.verbatim-lat1:4"
  },
  {
    "n": 12,
    "tagname": "lb",
    "char_offset": 212,
    "page": "1.48",
    "token_offset": "vero[2]",
    "urn": "urn:cts:greekLit:tlg0057.tlg002.verbatim-lat1:4"
  },
  {
    "n": 13,
    "tagname": "lb",
    "char_offset": 263,
    "page": "1.48",
    "token_offset": "optimae,[1]",
    "urn": "urn:cts:greekLit:tlg0057.tlg002.verbatim-lat1:4"
  },
  {
    "n": 14,
    "tagname": "lb",
    "char_offset": 318,
    "page": "1.48",
    "token_offset": "enim[1]",
    "urn": "urn:cts:greekLit:tlg0057.tlg002.verbatim-lat1:4"
  },
  {
    "n": 15,
    "tagname": "lb",
    "char_offset": 373,
    "page": "1.48",
    "token_offset": "incredibile[1]",
    "urn": "urn:cts:greekLit:tlg0057.tlg002.verbatim-lat1:4"
  },
  {
    "n": 16,
    "tagname": "lb",
    "char_offset": 432,
    "page": "1.48",
    "token_offset": "naturale[1]",
    "urn": "urn:cts:greekLit:tlg0057.tlg002.verbatim-lat1:4"
  },
  {
    "n": 17,
    "tagname": "lb",
    "char_offset": 479,
    "page": "1.48",
    "token_offset": "circulum[1]",
    "urn": "urn:cts:greekLit:tlg0057.tlg002.verbatim-lat1:4"
  },
  {
    "n": 18,
    "tagname": "lb",
    "char_offset": 537,
    "page": "1.48",
    "token_offset": "quae[1]",
    "urn": "urn:cts:greekLit:tlg0057.tlg002.verbatim-lat1:4"
  },
  {
    "n": "1.49",
    "tagname": "pb",
    "char_offset": 587,
    "token_offset": "paravit[1]",
    "urn": "urn:cts:greekLit:tlg0057.tlg002.verbatim-lat1:4"
  },
  {
    "n": 1,
    "tagname": "lb",
    "char_offset": 587,
    "page": "1.49",
    "token_offset": "paravit[1]",
    "urn": "urn:cts:greekLit:tlg0057.tlg002.verbatim-lat1:4"
  },
  {
    "n": 2,
    "tagname": "lb",
    "char_offset": 649,
    "page": "1.49",
    "token_offset": "instrumentis,[1]",
    "urn": "urn:cts:greekLit:tlg0057.tlg002.verbatim-lat1:4"
  },
  {
    "n": 3,
    "tagname": "lb",
    "char_offset": 697,
    "page": "1.49",
    "token_offset": "antiquius[1]",
    "urn": "urn:cts:greekLit:tlg0057.tlg002.verbatim-lat1:4"
  },
  {
    "n": 4,
    "tagname": "lb",
    "char_offset": 755,
    "page": "1.49",
    "token_offset": "auspicari.[1]",
    "urn": "urn:cts:greekLit:tlg0057.tlg002.verbatim-lat1:4"
  },
  {
    "n": 5,
    "tagname": "lb",
    "char_offset": 815,
    "page": "1.49",
    "token_offset": "credere,[1]",
    "urn": "urn:cts:greekLit:tlg0057.tlg002.verbatim-lat1:4"
  },
  {
    "n": 6,
    "tagname": "lb",
    "char_offset": 872,
    "page": "1.49",
    "token_offset": "vero[4]",
    "urn": "urn:cts:greekLit:tlg0057.tlg002.verbatim-lat1:4"
  },
  {
    "n": 7,
    "tagname": "lb",
    "char_offset": 926,
    "page": "1.49",
    "token_offset": "enim[4]",
    "urn": "urn:cts:greekLit:tlg0057.tlg002.verbatim-lat1:4"
  },
  {
    "n": 8,
    "tagname": "lb",
    "char_offset": 990,
    "page": "1.49",
    "token_offset": "judicaretur?[1]",
    "urn": "urn:cts:greekLit:tlg0057.tlg002.verbatim-lat1:4"
  },
  {
    "n": 9,
    "tagname": "lb",
    "char_offset": 1038,
    "page": "1.49",
    "token_offset": "linguae[1]",
    "urn": "urn:cts:greekLit:tlg0057.tlg002.verbatim-lat1:4"
  },
  {
    "tagname": "sic",
    "char_offset": 1064,
    "line": 10,
    "page": "1.49",
    "token_offset": "pomum,[1]",
    "urn": "urn:cts:greekLit:tlg0057.tlg002.verbatim-lat1:4",
    "end_char_offset": 1076,
    "end_token_offset": "cum[1]"
  },
  {
    "tagname": "corr",
    "char_offset": 1076,
    "line": 10,
    "page": "1.49",
    "token_offset": "cum[1]",
    "urn": "urn:cts:greekLit:tlg0057.tlg002.verbatim-lat1:4",
    "end_char_offset": 1088,
    "end_token_offset": "ficum[1]"
  },
  {
    "tagname": "choice",
    "char_offset": 1064,
    "line": 10,
    "page": "1.49",
    "token_offset": "pomum,[1]",
    "urn": "urn:cts:greekLit:tlg0057.tlg002.verbatim-lat1:4",
    "end_char_offset": 1088,
    "end_token_offset": "ficum[1]"
  },
  {
    "n": 10,
    "tagname": "lb",
    "char_offset": 1107,
    "page": "1.49",
    "token_offset": "credere?[1]",
    "urn": "urn:cts:greekLit:tlg0057.tlg002.verbatim-lat1:4"
  },
  {
    "n": 11,
    "tagname": "lb",
    "char_offset": 1161,
    "page": "1.49",
    "token_offset": "cupias[1]",
    "urn": "urn:cts:greekLit:tlg0057.tlg002.verbatim-lat1:4"
  },
  {
    "n": 12,
    "tagname": "lb",
    "char_offset": 1217,
    "page": "1.49",
    "token_offset": "tamquam[1]",
    "urn": "urn:cts:greekLit:tlg0057.tlg002.verbatim-lat1:4"
  },
  {
    "n": 13,
    "tagname": "lb",
    "char_offset": 1267,
    "page": "1.49",
    "token_offset": "non[7]",
    "urn": "urn:cts:greekLit:tlg0057.tlg002.verbatim-lat1:4"
  },
  {
    "n": 14,
    "tagname": "lb",
    "char_offset": 1321,
    "page": "1.49",
    "token_offset": "enim[5]",
    "urn": "urn:cts:greekLit:tlg0057.tlg002.verbatim-lat1:4"
  },
  {
    "n": 15,
    "tagname": "lb",
    "char_offset": 1374,
    "page": "1.49",
    "token_offset": "credere,[3]",
    "urn": "urn:cts:greekLit:tlg0057.tlg002.verbatim-lat1:4"
  },
  {
    "n": 16,
    "tagname": "lb",
    "char_offset": 1426,
    "page": "1.49",
    "token_offset": "sensilia[1]",
    "urn": "urn:cts:greekLit:tlg0057.tlg002.verbatim-lat1:4"
  },
  {
    "n": 17,
    "tagname": "lb",
    "char_offset": 1489,
    "page": "1.49",
    "token_offset": "intelligibilia[1]",
    "urn": "urn:cts:greekLit:tlg0057.tlg002.verbatim-lat1:4"
  },
  {
    "n": 18,
    "tagname": "lb",
    "char_offset": 1543,
    "page": "1.49",
    "token_offset": "credibilia[1]",
    "urn": "urn:cts:greekLit:tlg0057.tlg002.verbatim-lat1:4"
  },
  {
    "n": 19,
    "tagname": "lb",
    "char_offset": 1589,
    "page": "1.49",
    "token_offset": "instrumentis[1]",
    "urn": "urn:cts:greekLit:tlg0057.tlg002.verbatim-lat1:4"
  },
  {
    "n": "1.50",
    "tagname": "pb",
    "char_offset": 1641,
    "token_offset": "et[5]",
    "urn": "urn:cts:greekLit:tlg0057.tlg002.verbatim-lat1:4"
  },
  {
    "n": 1,
    "tagname": "lb",
    "char_offset": 1641,
    "page": "1.50",
    "token_offset": "et[5]",
    "urn": "urn:cts:greekLit:tlg0057.tlg002.verbatim-lat1:4"
  },
  {
    "n": 2,
    "tagname": "lb",
    "char_offset": 1701,
    "page": "1.50",
    "token_offset": "sibi[2]",
    "urn": "urn:cts:greekLit:tlg0057.tlg002.verbatim-lat1:4"
  },
  {
    "n": 3,
    "tagname": "lb",
    "char_offset": 1755,
    "page": "1.50",
    "token_offset": "et[6]",
    "urn": "urn:cts:greekLit:tlg0057.tlg002.verbatim-lat1:4"
  },
  {
    "n": 4,
    "tagname": "lb",
    "char_offset": 1815,
    "page": "1.50",
    "token_offset": "judicandi,[1]",
    "urn": "urn:cts:greekLit:tlg0057.tlg002.verbatim-lat1:4"
  },
  {
    "n": 5,
    "tagname": "lb",
    "char_offset": 1862,
    "page": "1.50",
    "token_offset": "ea,[4]",
    "urn": "urn:cts:greekLit:tlg0057.tlg002.verbatim-lat1:4"
  },
  {
    "n": 6,
    "tagname": "lb",
    "char_offset": 1922,
    "page": "1.50",
    "token_offset": "habet.[1]",
    "urn": "urn:cts:greekLit:tlg0057.tlg002.verbatim-lat1:4"
  },
  {
    "n": 7,
    "tagname": "lb",
    "char_offset": 1977,
    "page": "1.50",
    "token_offset": "intellectui[1]",
    "urn": "urn:cts:greekLit:tlg0057.tlg002.verbatim-lat1:4"
  },
  {
    "n": 8,
    "tagname": "lb",
    "char_offset": 2037,
    "page": "1.50",
    "token_offset": "non[9]",
    "urn": "urn:cts:greekLit:tlg0057.tlg002.verbatim-lat1:4"
  },
  {
    "n": 9,
    "tagname": "lb",
    "char_offset": 2090,
    "page": "1.50",
    "token_offset": "Ego[2]",
    "urn": "urn:cts:greekLit:tlg0057.tlg002.verbatim-lat1:4"
  },
  {
    "n": 10,
    "tagname": "lb",
    "char_offset": 2142,
    "page": "1.50",
    "token_offset": "instrumentis,[2]",
    "urn": "urn:cts:greekLit:tlg0057.tlg002.verbatim-lat1:4"
  },
  {
    "n": 11,
    "tagname": "lb",
    "char_offset": 2203,
    "page": "1.50",
    "token_offset": "invenias;[1]",
    "urn": "urn:cts:greekLit:tlg0057.tlg002.verbatim-lat1:4"
  },
  {
    "n": 12,
    "tagname": "lb",
    "char_offset": 2255,
    "page": "1.50",
    "token_offset": "tibi[1]",
    "urn": "urn:cts:greekLit:tlg0057.tlg002.verbatim-lat1:4"
  },
  {
    "n": 13,
    "tagname": "lb",
    "char_offset": 2308,
    "page": "1.50",
    "token_offset": "haec[2]",
    "urn": "urn:cts:greekLit:tlg0057.tlg002.verbatim-lat1:4"
  },
  {
    "n": 14,
    "tagname": "lb",
    "char_offset": 2364,
    "page": "1.50",
    "token_offset": "et[8]",
    "urn": "urn:cts:greekLit:tlg0057.tlg002.verbatim-lat1:4"
  },
  {
    "n": 15,
    "tagname": "lb",
    "char_offset": 2422,
    "page": "1.50",
    "token_offset": "quaeritur;[1]",
    "urn": "urn:cts:greekLit:tlg0057.tlg002.verbatim-lat1:4"
  },
  {
    "n": 16,
    "tagname": "lb",
    "char_offset": 2477,
    "page": "1.50",
    "token_offset": "inventionem[1]",
    "urn": "urn:cts:greekLit:tlg0057.tlg002.verbatim-lat1:4"
  },
  {
    "n": 17,
    "tagname": "lb",
    "char_offset": 2535,
    "page": "1.50",
    "token_offset": "eos,[2]",
    "urn": "urn:cts:greekLit:tlg0057.tlg002.verbatim-lat1:4"
  },
  {
    "n": 18,
    "tagname": "lb",
    "char_offset": 2587,
    "page": "1.50",
    "token_offset": "Quemadmodum[1]",
    "urn": "urn:cts:greekLit:tlg0057.tlg002.verbatim-lat1:4"
  },
  {
    "n": "1.51",
    "tagname": "pb",
    "char_offset": 2644,
    "token_offset": "indiget[1]",
    "urn": "urn:cts:greekLit:tlg0057.tlg002.verbatim-lat1:4"
  },
  {
    "n": 1,
    "tagname": "lb",
    "char_offset": 2644,
    "page": "1.51",
    "token_offset": "indiget[1]",
    "urn": "urn:cts:greekLit:tlg0057.tlg002.verbatim-lat1:4"
  },
  {
    "n": 2,
    "tagname": "lb",
    "char_offset": 2693,
    "page": "1.51",
    "token_offset": "aberrant:[1]",
    "urn": "urn:cts:greekLit:tlg0057.tlg002.verbatim-lat1:4"
  },
  {
    "n": 3,
    "tagname": "lb",
    "char_offset": 2748,
    "page": "1.51",
    "token_offset": "statim[2]",
    "urn": "urn:cts:greekLit:tlg0057.tlg002.verbatim-lat1:4"
  },
  {
    "type": "textpart",
    "subtype": "chapter",
    "n": "4",
    "content": "Cap. IV. Quod vero haec via docendi eos, qui aliquid addiscunt, qualem Favorinus intelligit, non solum inter caeteras non sit optima, sed nec doctrinam esse, ab initio abunde demonstratum arbitror. Reliquae vero omnes doctrinae quidem sunt; an vero sint optimae, videamus, primum ab iisdem rursus incipientes: id enim nobis et manifestum apparet, quamvis illud incredibile reddere conentur sophistae, nullum videlicet esse naturale judicandi instrumentum. Circinus enim circulum describit, cubitus magnitudinem discernit, ut libra, quae pondus habent. Haec autem omnia ipse sibi paravit homo naturalibus organis, et judicandi impulsus instrumentis, ultra quae judicandi instrumentum nec antiquius habemus, nec praestantius; hinc igitur oportet auspicari. Rursus enim dicit animus, quod nobis possibile est credere, vel non credere naturali judicandi instrumento, hoc vero non est possibile alio instrumento judicare; quo enim judicantur caetera omnia, quomodo et illud ab alio judicaretur? vis credere oculis clare videntibus, et linguae gustanti, hoc esse pomum, illudfi cum illud ficum , vel non credere? Concedam quicquid nobiscum volueris facere; si cupias mecum disputare: a te vero non credente recedam tamquam affecto praetor naturum. Primo supponatur, te non credere, nec quicquam sperare ex me discere (hoc enim nuper abstinui dicere). Supponatur vero, te credere, sperare ex me judicium addiscere. Ego vero sensilia per ea, quae evidenter a sensibus percipiuntur, intelligibilia vero per ea, quae intellectu concipiuntur, credibilia judico. Cum autem ex naturalibus instrumentis judicandi artes omnes constituantur, organa vero et instrumenta judicandi artificialia, per quae alia ipsi sibi componunt, alia autem ab aliis composita judicant, et ego ostendam in universum, organa et instrumenta judicandi, tum ea, quibus parabis veras rationes, cum ea, quibus ab aliis allatas judicabis. Totum enim sic se habet. Siquid enim ex se ipso appareat sensui vel intellectui manifeste, disquisitione non indigebit; at si quid tale non exsistat, quae ab alio sumitur, eget cognitione. Ego vero me polliceor te docturum quaedam instrumentis, quae ab arte fiunt, respondentia, quibus quaesitum invenias; alia vero judicandi instrumentis, quibus, quod tibi videbitur, inventum fuisse judicabis. Cum autem haec didiceris, multis te exemplis exercebo, ut celeriter et perfecte invenire possis, et judicare id, quod quaeritur; ita ut nullo jam amplius libro indigeas ad inventionem veri, nullave alia institutione, et statim dignoscas eos, qui dicunt alia ab iis, quae inveneris. Quemadmodum enim, qui cognoscit rectam viam esse rectam, non indiget alia doctrina ad redarguendum eos, qui aberrant: sic et qui rectam demonstrationis viam didicit, statim simul per ipsam cognoscit erroneas.",
    "line": 4,
    "page": "1.51",
    "tokens": [
      "Cap.",
      "IV.",
      "Quod",
      "vero",
      "haec",
      "via",
      "docendi",
      "eos,",
      "qui",
      "aliquid",
      "addiscunt,",
      "qualem",
      "Favorinus",
      "intelligit,",
      "non",
      "solum",
      "inter",
      "caeteras",
      "non",
      "sit",
      "optima,",
      "sed",
      "nec",
      "doctrinam",
      "esse,",
      "ab",
      "initio",
      "abunde",
      "demonstratum",
      "arbitror.",
      "Reliquae",
      "vero",
      "omnes",
      "doctrinae",
      "quidem",
      "sunt;",
      "an",
      "vero",
      "sint",
      "optimae,",
      "videamus,",
      "primum",
      "ab",
      "iisdem",
      "rursus",
      "incipientes:",
      "id",
      "enim",
      "nobis",
      "et",
      "manifestum",
      "apparet,",
      "quamvis",
      "illud",
      "incredibile",
      "reddere",
      "conentur",
      "sophistae,",
      "nullum",
      "videlicet",
      "esse",
      "naturale",
      "judicandi",
      "instrumentum.",
      "Circinus",
      "enim",
      "circulum",
      "describit,",
      "cubitus",
      "magnitudinem",
      "discernit,",
      "ut",
      "libra,",
      "quae",
      "pondus",
      "habent.",
      "Haec",
      "autem",
      "omnia",
      "ipse",
      "sibi",
      "paravit",
      "homo",
      "naturalibus",
      "organis,",
      "et",
      "judicandi",
      "impulsus",
      "instrumentis,",
      "ultra",
      "quae",
      "judicandi",
      "instrumentum",
      "nec",
      "antiquius",
      "habemus,",
      "nec",
      "praestantius;",
      "hinc",
      "igitur",
      "oportet",
      "auspicari.",
      "Rursus",
      "enim",
      "dicit",
      "animus,",
      "quod",
      "nobis",
      "possibile",
      "est",
      "credere,",
      "vel",
      "non",
      "credere",
      "naturali",
      "judicandi",
      "instrumento,",
      "hoc",
      "vero",
      "non",
      "est",
      "possibile",
      "alio",
      "instrumento",
      "judicare;",
      "quo",
      "enim",
      "judicantur",
      "caetera",
      "omnia,",
      "quomodo",
      "et",
      "illud",
      "ab",
      "alio",
      "judicaretur?",
      "vis",
      "credere",
      "oculis",
      "clare",
      "videntibus,",
      "et",
      "linguae",
      "gustanti,",
      "hoc",
      "esse",
      "pomum,",
      "illudfi",
      "cum",
      "illud",
      "ficum",
      ",",
      "vel",
      "non",
      "credere?",
      "Concedam",
      "quicquid",
      "nobiscum",
      "volueris",
      "facere;",
      "si",
      "cupias",
      "mecum",
      "disputare:",
      "a",
      "te",
      "vero",
      "non",
      "credente",
      "recedam",
      "tamquam",
      "affecto",
      "praetor",
      "naturum.",
      "Primo",
      "supponatur,",
      "te",
      "non",
      "credere,",
      "nec",
      "quicquam",
      "sperare",
      "ex",
      "me",
      "discere",
      "(hoc",
      "enim",
      "nuper",
      "abstinui",
      "dicere).",
      "Supponatur",
      "vero,",
      "te",
      "credere,",
      "sperare",
      "ex",
      "me",
      "judicium",
      "addiscere.",
      "Ego",
      "vero",
      "sensilia",
      "per",
      "ea,",
      "quae",
      "evidenter",
      "a",
      "sensibus",
      "percipiuntur,",
      "intelligibilia",
      "vero",
      "per",
      "ea,",
      "quae",
      "intellectu",
      "concipiuntur,",
      "credibilia",
      "judico.",
      "Cum",
      "autem",
      "ex",
      "naturalibus",
      "instrumentis",
      "judicandi",
      "artes",
      "omnes",
      "constituantur,",
      "organa",
      "vero",
      "et",
      "instrumenta",
      "judicandi",
      "artificialia,",
      "per",
      "quae",
      "alia",
      "ipsi",
      "sibi",
      "componunt,",
      "alia",
      "autem",
      "ab",
      "aliis",
      "composita",
      "judicant,",
      "et",
      "ego",
      "ostendam",
      "in",
      "universum,",
      "organa",
      "et",
      "instrumenta",
      "judicandi,",
      "tum",
      "ea,",
      "quibus",
      "parabis",
      "veras",
      "rationes,",
      "cum",
      "ea,",
      "quibus",
      "ab",
      "aliis",
      "allatas",
      "judicabis.",
      "Totum",
      "enim",
      "sic",
      "se",
      "habet.",
      "Siquid",
      "enim",
      "ex",
      "se",
      "ipso",
      "appareat",
      "sensui",
      "vel",
      "intellectui",
      "manifeste,",
      "disquisitione",
      "non",
      "indigebit;",
      "at",
      "si",
      "quid",
      "tale",
      "non",
      "exsistat,",
      "quae",
      "ab",
      "alio",
      "sumitur,",
      "eget",
      "cognitione.",
      "Ego",
      "vero",
      "me",
      "polliceor",
      "te",
      "docturum",
      "quaedam",
      "instrumentis,",
      "quae",
      "ab",
      "arte",
      "fiunt,",
      "respondentia,",
      "quibus",
      "quaesitum",
      "invenias;",
      "alia",
      "vero",
      "judicandi",
      "instrumentis,",
      "quibus,",
      "quod",
      "tibi",
      "videbitur,",
      "inventum",
      "fuisse",
      "judicabis.",
      "Cum",
      "autem",
      "haec",
      "didiceris,",
      "multis",
      "te",
      "exemplis",
      "exercebo,",
      "ut",
      "celeriter",
      "et",
      "perfecte",
      "invenire",
      "possis,",
      "et",
      "judicare",
      "id,",
      "quod",
      "quaeritur;",
      "ita",
      "ut",
      "nullo",
      "jam",
      "amplius",
      "libro",
      "indigeas",
      "ad",
      "inventionem",
      "veri,",
      "nullave",
      "alia",
      "institutione,",
      "et",
      "statim",
      "dignoscas",
      "eos,",
      "qui",
      "dicunt",
      "alia",
      "ab",
      "iis,",
      "quae",
      "inveneris.",
      "Quemadmodum",
      "enim,",
      "qui",
      "cognoscit",
      "rectam",
      "viam",
      "esse",
      "rectam,",
      "non",
      "indiget",
      "alia",
      "doctrina",
      "ad",
      "redarguendum",
      "eos,",
      "qui",
      "aberrant:",
      "sic",
      "et",
      "qui",
      "rectam",
      "demonstrationis",
      "viam",
      "didicit,",
      "statim",
      "simul",
      "per",
      "ipsam",
      "cognoscit",
      "erroneas."
    ],
    "urn": "urn:cts:greekLit:tlg0057.tlg002.verbatim-lat1:4"
  },
  {
    "n": 4,
    "tagname": "lb",
    "char_offset": 0,
    "page": "1.51",
    "token_offset": null,
    "urn": "urn:cts:greekLit:tlg0057.tlg002.verbatim-lat1:5"
  },
  {
    "rend": "indent",
    "tagname": "p",
    "char_offset": 0,
    "line": 4,
    "page": "1.51",
    "token_offset": null,
    "urn": "urn:cts:greekLit:tlg0057.tlg002.verbatim-lat1:5",
    "end_char_offset": 0,
    "end_token_offset": null
  },
  {
    "value": "5",
    "tagname": "num",
    "char_offset": 0,
    "line": 5,
    "page": "1.51",
    "token_offset": null,
    "urn": "urn:cts:greekLit:tlg0057.tlg002.verbatim-lat1:5",
    "end_char_offset": 8,
    "end_token_offset": "V.[1]"
  },
  {
    "type": "head",
    "tagname": "label",
    "char_offset": 0,
    "line": 5,
    "page": "1.51",
    "token_offset": null,
    "urn": "urn:cts:greekLit:tlg0057.tlg002.verbatim-lat1:5",
    "end_char_offset": 8,
    "end_token_offset": "V.[1]"
  },
  {
    "n": 5,
    "tagname": "lb",
    "char_offset": 54,
    "page": "1.51",
    "token_offset": "facere,[1]",
    "urn": "urn:cts:greekLit:tlg0057.tlg002.verbatim-lat1:5"
  },
  {
    "tagname": "sic",
    "char_offset": 82,
    "line": 6,
    "page": "1.51",
    "token_offset": "esse[1]",
    "urn": "urn:cts:greekLit:tlg0057.tlg002.verbatim-lat1:5",
    "end_char_offset": 89,
    "end_token_offset": "coecum[1]"
  },
  {
    "tagname": "corr",
    "char_offset": 89,
    "line": 6,
    "page": "1.51",
    "token_offset": "coecum[1]",
    "urn": "urn:cts:greekLit:tlg0057.tlg002.verbatim-lat1:5",
    "end_char_offset": 96,
    "end_token_offset": "caecum[1]"
  },
  {
    "tagname": "choice",
    "char_offset": 82,
    "line": 6,
    "page": "1.51",
    "token_offset": "esse[1]",
    "urn": "urn:cts:greekLit:tlg0057.tlg002.verbatim-lat1:5",
    "end_char_offset": 96,
    "end_token_offset": "caecum[1]"
  },
  {
    "n": 6,
    "tagname": "lb",
    "char_offset": 124,
    "page": "1.51",
    "token_offset": "quis[2]",
    "urn": "urn:cts:greekLit:tlg0057.tlg002.verbatim-lat1:5"
  },
  {
    "n": 7,
    "tagname": "lb",
    "char_offset": 186,
    "page": "1.51",
    "token_offset": "qui[1]",
    "urn": "urn:cts:greekLit:tlg0057.tlg002.verbatim-lat1:5"
  },
  {
    "n": 8,
    "tagname": "lb",
    "char_offset": 247,
    "page": "1.51",
    "token_offset": "atqui[1]",
    "urn": "urn:cts:greekLit:tlg0057.tlg002.verbatim-lat1:5"
  },
  {
    "n": 9,
    "tagname": "lb",
    "char_offset": 305,
    "page": "1.51",
    "token_offset": "aut,[1]",
    "urn": "urn:cts:greekLit:tlg0057.tlg002.verbatim-lat1:5"
  },
  {
    "n": 10,
    "tagname": "lb",
    "char_offset": 360,
    "page": "1.51",
    "token_offset": "quoniam[1]",
    "urn": "urn:cts:greekLit:tlg0057.tlg002.verbatim-lat1:5"
  },
  {
    "n": 11,
    "tagname": "lb",
    "char_offset": 415,
    "page": "1.51",
    "token_offset": "quae[1]",
    "urn": "urn:cts:greekLit:tlg0057.tlg002.verbatim-lat1:5"
  },
  {
    "n": 12,
    "tagname": "lb",
    "char_offset": 472,
    "page": "1.51",
    "token_offset": "Quemadmodum[1]",
    "urn": "urn:cts:greekLit:tlg0057.tlg002.verbatim-lat1:5"
  },
  {
    "n": 13,
    "tagname": "lb",
    "char_offset": 523,
    "page": "1.51",
    "token_offset": "carent;[1]",
    "urn": "urn:cts:greekLit:tlg0057.tlg002.verbatim-lat1:5"
  },
  {
    "n": 14,
    "tagname": "lb",
    "char_offset": 571,
    "page": "1.51",
    "token_offset": "fides[1]",
    "urn": "urn:cts:greekLit:tlg0057.tlg002.verbatim-lat1:5"
  },
  {
    "n": 15,
    "tagname": "lb",
    "char_offset": 623,
    "page": "1.51",
    "token_offset": "judicandum[1]",
    "urn": "urn:cts:greekLit:tlg0057.tlg002.verbatim-lat1:5"
  },
  {
    "n": 16,
    "tagname": "lb",
    "char_offset": 686,
    "page": "1.51",
    "token_offset": "instrumentum[1]",
    "urn": "urn:cts:greekLit:tlg0057.tlg002.verbatim-lat1:5"
  },
  {
    "n": 17,
    "tagname": "lb",
    "char_offset": 729,
    "page": "1.51",
    "token_offset": "Ridiculus[1]",
    "urn": "urn:cts:greekLit:tlg0057.tlg002.verbatim-lat1:5"
  },
  {
    "n": 18,
    "tagname": "lb",
    "char_offset": 788,
    "page": "1.51",
    "token_offset": "nisi[1]",
    "urn": "urn:cts:greekLit:tlg0057.tlg002.verbatim-lat1:5"
  },
  {
    "n": 19,
    "tagname": "lb",
    "char_offset": 847,
    "page": "1.51",
    "token_offset": "nihil[2]",
    "urn": "urn:cts:greekLit:tlg0057.tlg002.verbatim-lat1:5"
  },
  {
    "n": "1.52",
    "tagname": "pb",
    "char_offset": 899,
    "token_offset": "rerum[1]",
    "urn": "urn:cts:greekLit:tlg0057.tlg002.verbatim-lat1:5"
  },
  {
    "n": 1,
    "tagname": "lb",
    "char_offset": 899,
    "page": "1.52",
    "token_offset": "rerum[1]",
    "urn": "urn:cts:greekLit:tlg0057.tlg002.verbatim-lat1:5"
  },
  {
    "n": 2,
    "tagname": "lb",
    "char_offset": 953,
    "page": "1.52",
    "token_offset": "oculus[1]",
    "urn": "urn:cts:greekLit:tlg0057.tlg002.verbatim-lat1:5"
  },
  {
    "n": 3,
    "tagname": "lb",
    "char_offset": 1004,
    "page": "1.52",
    "token_offset": "omnibus[1]",
    "urn": "urn:cts:greekLit:tlg0057.tlg002.verbatim-lat1:5"
  },
  {
    "n": 4,
    "tagname": "lb",
    "char_offset": 1056,
    "page": "1.52",
    "token_offset": "qui[2]",
    "urn": "urn:cts:greekLit:tlg0057.tlg002.verbatim-lat1:5"
  },
  {
    "n": 5,
    "tagname": "lb",
    "char_offset": 1118,
    "page": "1.52",
    "token_offset": "obscurius,[1]",
    "urn": "urn:cts:greekLit:tlg0057.tlg002.verbatim-lat1:5"
  },
  {
    "n": 6,
    "tagname": "lb",
    "char_offset": 1169,
    "page": "1.52",
    "token_offset": "caeteris[1]",
    "urn": "urn:cts:greekLit:tlg0057.tlg002.verbatim-lat1:5"
  },
  {
    "n": 7,
    "tagname": "lb",
    "char_offset": 1223,
    "page": "1.52",
    "token_offset": "intelligibilis,[1]",
    "urn": "urn:cts:greekLit:tlg0057.tlg002.verbatim-lat1:5"
  },
  {
    "n": 8,
    "tagname": "lb",
    "char_offset": 1276,
    "page": "1.52",
    "token_offset": "caecutientem,[1]",
    "urn": "urn:cts:greekLit:tlg0057.tlg002.verbatim-lat1:5"
  },
  {
    "n": 9,
    "tagname": "lb",
    "char_offset": 1331,
    "page": "1.52",
    "token_offset": "fateor,[1]",
    "urn": "urn:cts:greekLit:tlg0057.tlg002.verbatim-lat1:5"
  },
  {
    "n": 10,
    "tagname": "lb",
    "char_offset": 1381,
    "page": "1.52",
    "token_offset": "de[2]",
    "urn": "urn:cts:greekLit:tlg0057.tlg002.verbatim-lat1:5"
  },
  {
    "n": 11,
    "tagname": "lb",
    "char_offset": 1431,
    "page": "1.52",
    "token_offset": "evidens[2]",
    "urn": "urn:cts:greekLit:tlg0057.tlg002.verbatim-lat1:5"
  },
  {
    "n": 12,
    "tagname": "lb",
    "char_offset": 1487,
    "page": "1.52",
    "token_offset": "quomodo[1]",
    "urn": "urn:cts:greekLit:tlg0057.tlg002.verbatim-lat1:5"
  },
  {
    "n": 13,
    "tagname": "lb",
    "char_offset": 1543,
    "page": "1.52",
    "token_offset": "principiis[1]",
    "urn": "urn:cts:greekLit:tlg0057.tlg002.verbatim-lat1:5"
  },
  {
    "n": 14,
    "tagname": "lb",
    "char_offset": 1593,
    "page": "1.52",
    "token_offset": "est[6]",
    "urn": "urn:cts:greekLit:tlg0057.tlg002.verbatim-lat1:5"
  },
  {
    "n": 15,
    "tagname": "lb",
    "char_offset": 1648,
    "page": "1.52",
    "token_offset": "totum[1]",
    "urn": "urn:cts:greekLit:tlg0057.tlg002.verbatim-lat1:5"
  },
  {
    "n": 16,
    "tagname": "lb",
    "char_offset": 1703,
    "page": "1.52",
    "token_offset": "quidem[1]",
    "urn": "urn:cts:greekLit:tlg0057.tlg002.verbatim-lat1:5"
  },
  {
    "n": 17,
    "tagname": "lb",
    "char_offset": 1759,
    "page": "1.52",
    "token_offset": "nobiscum[1]",
    "urn": "urn:cts:greekLit:tlg0057.tlg002.verbatim-lat1:5"
  },
  {
    "n": 18,
    "tagname": "lb",
    "char_offset": 1820,
    "page": "1.52",
    "token_offset": "cognoscibile,[1]",
    "urn": "urn:cts:greekLit:tlg0057.tlg002.verbatim-lat1:5"
  },
  {
    "type": "textpart",
    "subtype": "chapter",
    "n": "5",
    "content": "Cap. V. Favorinus vero mihi videtur similiter facere, ac si quis diceret, te esse coecum caecum , posse vero judicare, quis nostrum sit sordidior, aut candidior, non cogitans, quod, qui talia judicaturus est, ei prius oporteat inesse visum: atqui nihil refert ad judicandum, non omnino visum habere, aut, cum habeas, ei non credere. Eodem quoque modo, quoniam id, quo judicamus, tale aliquid est, et, quoniam, quae eidem sunt aequalia, inter se sunt aequalia. Quemadmodum asinis nemo judicare permittet, quia mente carent; ita nec hominibus, si mentem habeant, cui fides non possit haberi. Nihil enim differt ad judicandum doctrinarum incertitudinem, vel nullo modo habere instrumentum judicandi, vel ipsi non credere. Ridiculus est igitur Favorinus, permittens judicium discipulis, nisi concedat fidem ipsis instrumentis judicandi. Si enim nihil evidens intellectui, quamvis ex se credibile, rerum omnium perit judicium; si autem sit quidem, ut oculus in corpore, ita mens in anima, non equidem omnibus aeque perspicax, consentaneum est, quemadmodum, qui cernit acutius, adducit ad visibile eum, qui videt obscurius, simili modo in intellectionibus; qui enim caeteris antecellit in evidenti cognitione rei intelligibilis, ad ejus contemplationem adducit maxime caecutientem, et hic est praeceptor, ut inquit Plato, et ego fateor, et de his scriptum est a me fusius in tractatu de demonstratione, quoniam talis est quaedam evidens doctrina ad intellectionem. Scriptum est autem, quomodo quis exorsus in unaquaque re ab elementis et principiis possit maxime demonstrare, quicquid possibile est demonstrari; non ut mirandus ille Favorinus, qui totum unum librum scripsit, in quo ostendit, ne solem quidem esse comprehensibilem, et quasi cum obliviosis nobiscum alibi disputat, conceditque aliquid certo esse cognoscibile, et illud discipulis eligere permittit.",
    "line": 19,
    "page": "1.52",
    "tokens": [
      "Cap.",
      "V.",
      "Favorinus",
      "vero",
      "mihi",
      "videtur",
      "similiter",
      "facere,",
      "ac",
      "si",
      "quis",
      "diceret,",
      "te",
      "esse",
      "coecum",
      "caecum",
      ",",
      "posse",
      "vero",
      "judicare,",
      "quis",
      "nostrum",
      "sit",
      "sordidior,",
      "aut",
      "candidior,",
      "non",
      "cogitans,",
      "quod,",
      "qui",
      "talia",
      "judicaturus",
      "est,",
      "ei",
      "prius",
      "oporteat",
      "inesse",
      "visum:",
      "atqui",
      "nihil",
      "refert",
      "ad",
      "judicandum,",
      "non",
      "omnino",
      "visum",
      "habere,",
      "aut,",
      "cum",
      "habeas,",
      "ei",
      "non",
      "credere.",
      "Eodem",
      "quoque",
      "modo,",
      "quoniam",
      "id,",
      "quo",
      "judicamus,",
      "tale",
      "aliquid",
      "est,",
      "et,",
      "quoniam,",
      "quae",
      "eidem",
      "sunt",
      "aequalia,",
      "inter",
      "se",
      "sunt",
      "aequalia.",
      "Quemadmodum",
      "asinis",
      "nemo",
      "judicare",
      "permittet,",
      "quia",
      "mente",
      "carent;",
      "ita",
      "nec",
      "hominibus,",
      "si",
      "mentem",
      "habeant,",
      "cui",
      "fides",
      "non",
      "possit",
      "haberi.",
      "Nihil",
      "enim",
      "differt",
      "ad",
      "judicandum",
      "doctrinarum",
      "incertitudinem,",
      "vel",
      "nullo",
      "modo",
      "habere",
      "instrumentum",
      "judicandi,",
      "vel",
      "ipsi",
      "non",
      "credere.",
      "Ridiculus",
      "est",
      "igitur",
      "Favorinus,",
      "permittens",
      "judicium",
      "discipulis,",
      "nisi",
      "concedat",
      "fidem",
      "ipsis",
      "instrumentis",
      "judicandi.",
      "Si",
      "enim",
      "nihil",
      "evidens",
      "intellectui,",
      "quamvis",
      "ex",
      "se",
      "credibile,",
      "rerum",
      "omnium",
      "perit",
      "judicium;",
      "si",
      "autem",
      "sit",
      "quidem,",
      "ut",
      "oculus",
      "in",
      "corpore,",
      "ita",
      "mens",
      "in",
      "anima,",
      "non",
      "equidem",
      "omnibus",
      "aeque",
      "perspicax,",
      "consentaneum",
      "est,",
      "quemadmodum,",
      "qui",
      "cernit",
      "acutius,",
      "adducit",
      "ad",
      "visibile",
      "eum,",
      "qui",
      "videt",
      "obscurius,",
      "simili",
      "modo",
      "in",
      "intellectionibus;",
      "qui",
      "enim",
      "caeteris",
      "antecellit",
      "in",
      "evidenti",
      "cognitione",
      "rei",
      "intelligibilis,",
      "ad",
      "ejus",
      "contemplationem",
      "adducit",
      "maxime",
      "caecutientem,",
      "et",
      "hic",
      "est",
      "praeceptor,",
      "ut",
      "inquit",
      "Plato,",
      "et",
      "ego",
      "fateor,",
      "et",
      "de",
      "his",
      "scriptum",
      "est",
      "a",
      "me",
      "fusius",
      "in",
      "tractatu",
      "de",
      "demonstratione,",
      "quoniam",
      "talis",
      "est",
      "quaedam",
      "evidens",
      "doctrina",
      "ad",
      "intellectionem.",
      "Scriptum",
      "est",
      "autem,",
      "quomodo",
      "quis",
      "exorsus",
      "in",
      "unaquaque",
      "re",
      "ab",
      "elementis",
      "et",
      "principiis",
      "possit",
      "maxime",
      "demonstrare,",
      "quicquid",
      "possibile",
      "est",
      "demonstrari;",
      "non",
      "ut",
      "mirandus",
      "ille",
      "Favorinus,",
      "qui",
      "totum",
      "unum",
      "librum",
      "scripsit,",
      "in",
      "quo",
      "ostendit,",
      "ne",
      "solem",
      "quidem",
      "esse",
      "comprehensibilem,",
      "et",
      "quasi",
      "cum",
      "obliviosis",
      "nobiscum",
      "alibi",
      "disputat,",
      "conceditque",
      "aliquid",
      "certo",
      "esse",
      "cognoscibile,",
      "et",
      "illud",
      "discipulis",
      "eligere",
      "permittit."
    ],
    "urn": "urn:cts:greekLit:tlg0057.tlg002.verbatim-lat1:5"
  }
]